{
  "nodes": [
    {
      "id": "F4Lo07Ls2uXZHq9pHEH73",
      "text": "Is APT-Q responsible for the intrusion at ACME?",
      "x": 420,
      "y": 40,
      "createdAt": "2026-07-06T22:26:04.725Z",
      "stale": {
        "kind": "fresh"
      },
      "type": "question",
      "threadId": "F4Lo07Ls2uXZHq9pHEH73",
      "status": "open",
      "mutuallyExclusive": true
    },
    {
      "id": "1kMNXyC-mMe4Z_tyEK9hz",
      "text": "A criminal affiliate reused APT-Q tooling",
      "x": 430,
      "y": 230,
      "createdAt": "2026-07-06T22:29:59.725Z",
      "stale": {
        "kind": "fresh"
      },
      "type": "claim",
      "threadId": "F4Lo07Ls2uXZHq9pHEH73",
      "status": "open",
      "likelihood": "realistic_possibility",
      "confidence": "low"
    },
    {
      "id": "J59lyA1PwKWOgP0p9AQc0",
      "text": "APT-Q conducted the intrusion",
      "x": 140,
      "y": 230,
      "createdAt": "2026-07-06T22:27:38.725Z",
      "stale": {
        "kind": "undermined",
        "causeEventId": "lzV-nzKpz9LaYzvsyPiNA"
      },
      "type": "claim",
      "threadId": "F4Lo07Ls2uXZHq9pHEH73",
      "status": "open",
      "likelihood": "likely",
      "confidence": "moderate"
    },
    {
      "id": "JUgKHcme2oRbzU-6FZZe2",
      "text": "An insider staged the intrusion to look external",
      "x": 720,
      "y": 230,
      "createdAt": "2026-07-06T22:32:20.725Z",
      "stale": {
        "kind": "undermined",
        "causeEventId": "lzV-nzKpz9LaYzvsyPiNA"
      },
      "type": "claim",
      "threadId": "F4Lo07Ls2uXZHq9pHEH73",
      "status": "open",
      "likelihood": "unlikely",
      "confidence": "low"
    },
    {
      "id": "GeiY5JM8dUvdaZb8Z6q9r",
      "text": "ACME's VPN logs are complete and untampered",
      "x": 640,
      "y": 430,
      "createdAt": "2026-07-08T22:30:46.725Z",
      "stale": {
        "kind": "fresh"
      },
      "type": "assumption",
      "threadId": "F4Lo07Ls2uXZHq9pHEH73",
      "linchpin": false,
      "validity": "supported"
    },
    {
      "id": "Goz2EzUOhdS4E-KfxNRVL",
      "text": "Access implies intent",
      "x": 880,
      "y": 430,
      "createdAt": "2026-07-08T22:32:20.725Z",
      "stale": {
        "kind": "fresh"
      },
      "type": "assumption",
      "threadId": "F4Lo07Ls2uXZHq9pHEH73",
      "linchpin": true,
      "validity": "unsupported"
    },
    {
      "id": "Lm-7BtyHi0xd-0byWGxG2",
      "text": "Code overlap implies common authorship",
      "x": 60,
      "y": 430,
      "createdAt": "2026-07-08T22:27:38.725Z",
      "stale": {
        "kind": "fresh"
      },
      "type": "assumption",
      "threadId": "F4Lo07Ls2uXZHq9pHEH73",
      "linchpin": true,
      "validity": "caveated",
      "abandonTrigger": "KESTREL source or builder leaks publicly"
    },
    {
      "id": "QjWh6X0AYPGX8p-I2CgFF",
      "text": "APT-Q does not share infrastructure with affiliates",
      "x": 300,
      "y": 430,
      "createdAt": "2026-07-08T22:34:41.725Z",
      "stale": {
        "kind": "fresh"
      },
      "type": "assumption",
      "threadId": "F4Lo07Ls2uXZHq9pHEH73",
      "linchpin": false,
      "validity": "caveated"
    },
    {
      "id": "wKdNsTR7D9Nqa3Uj0umEF",
      "text": "Loader shares code with APT-Q's KESTREL implant",
      "x": 80,
      "y": 640,
      "createdAt": "2026-07-08T22:39:23.725Z",
      "stale": {
        "kind": "fresh"
      },
      "type": "evidence",
      "threadId": "F4Lo07Ls2uXZHq9pHEH73",
      "sourceReliability": "B",
      "infoCredibility": 3
    },
    {
      "id": "cNK0zJjA5FEzGP5fehN0b",
      "text": "VPN logs show access from inside the HQ subnet",
      "x": 800,
      "y": 640,
      "createdAt": "2026-07-08T22:47:13.725Z",
      "stale": {
        "kind": "fresh"
      },
      "type": "evidence",
      "threadId": "F4Lo07Ls2uXZHq9pHEH73",
      "sourceReliability": "D",
      "infoCredibility": 4
    },
    {
      "id": "DKKqs5O4yDwEaaS5aNSnY",
      "text": "C2 infrastructure overlaps a 2024 APT-Q campaign",
      "x": 320,
      "y": 640,
      "createdAt": "2026-07-08T22:42:31.725Z",
      "stale": {
        "kind": "fresh"
      },
      "type": "evidence",
      "threadId": "F4Lo07Ls2uXZHq9pHEH73",
      "sourceReliability": "B",
      "infoCredibility": 3
    },
    {
      "id": "lOcH6_eyof6KJOU2Wl6xv",
      "text": "Commodity credential-dumping tools used throughout",
      "x": 560,
      "y": 640,
      "createdAt": "2026-07-08T22:44:52.725Z",
      "stale": {
        "kind": "fresh"
      },
      "type": "evidence",
      "threadId": "F4Lo07Ls2uXZHq9pHEH73",
      "sourceReliability": "C",
      "infoCredibility": 3
    },
    {
      "id": "6EmdJnCl1l0_vF4SP40IG",
      "text": "Ransom note demands payment in Monero",
      "x": 460,
      "y": 800,
      "createdAt": "2026-07-08T22:54:16.725Z",
      "stale": {
        "kind": "fresh"
      },
      "type": "evidence",
      "threadId": "F4Lo07Ls2uXZHq9pHEH73",
      "sourceReliability": "C",
      "infoCredibility": 2
    },
    {
      "id": "BEoS8RZFx2E1I2qk0d5f2",
      "text": "APT-Q is known to sell tooling to affiliates",
      "x": 200,
      "y": 800,
      "createdAt": "2026-07-08T22:51:55.725Z",
      "stale": {
        "kind": "fresh"
      },
      "type": "evidence",
      "threadId": "F4Lo07Ls2uXZHq9pHEH73",
      "sourceReliability": "B",
      "infoCredibility": 2
    },
    {
      "id": "jL_3WrN01R7_5DcN2VPGH",
      "text": "Phishing lure written in fluent corporate English",
      "x": 1040,
      "y": 640,
      "createdAt": "2026-07-08T22:49:34.725Z",
      "stale": {
        "kind": "fresh"
      },
      "type": "evidence",
      "threadId": "F4Lo07Ls2uXZHq9pHEH73",
      "sourceReliability": "C",
      "infoCredibility": 3
    },
    {
      "id": "iSShZhcofDGMCk7Fm2LQ3",
      "text": "Forum chatter claims an insider sold ACME access",
      "x": 720,
      "y": 800,
      "createdAt": "2026-07-08T22:56:37.725Z",
      "stale": {
        "kind": "fresh"
      },
      "type": "evidence",
      "threadId": "F4Lo07Ls2uXZHq9pHEH73",
      "sourceNote": "Single dark-web forum post, unverified"
    },
    {
      "id": "edWnPwcXCSAfJnQc_cb6G",
      "text": "Was the loader custom-built?",
      "x": 60,
      "y": 60,
      "createdAt": "2026-07-08T23:13:04.725Z",
      "stale": {
        "kind": "fresh"
      },
      "type": "question",
      "threadId": "edWnPwcXCSAfJnQc_cb6G",
      "status": "answered",
      "mutuallyExclusive": false,
      "parentThreadId": "F4Lo07Ls2uXZHq9pHEH73"
    },
    {
      "id": "kFKpiOCof28uB0RWmoYL3",
      "text": "The loader was assembled from a leaked builder",
      "x": 460,
      "y": 240,
      "createdAt": "2026-07-08T23:16:12.725Z",
      "stale": {
        "kind": "fresh"
      },
      "type": "claim",
      "threadId": "edWnPwcXCSAfJnQc_cb6G",
      "status": "open",
      "likelihood": "unlikely",
      "confidence": "low"
    },
    {
      "id": "O1EZzp-7ROLVuI10h51tp",
      "text": "The loader was custom-built for this intrusion",
      "x": 160,
      "y": 240,
      "createdAt": "2026-07-08T23:13:51.725Z",
      "stale": {
        "kind": "fresh"
      },
      "type": "claim",
      "threadId": "edWnPwcXCSAfJnQc_cb6G",
      "status": "adopted",
      "likelihood": "likely",
      "confidence": "high"
    },
    {
      "id": "X6Ws-hHkbBG7POvuE4mEL",
      "text": "No builder artifacts for this loader found in the wild",
      "x": 300,
      "y": 480,
      "createdAt": "2026-07-08T23:20:07.725Z",
      "stale": {
        "kind": "fresh"
      },
      "type": "evidence",
      "threadId": "edWnPwcXCSAfJnQc_cb6G",
      "sourceReliability": "C",
      "infoCredibility": 2
    },
    {
      "id": "FyQcj2ky8tpl1dautOBRY",
      "text": "The loader was custom-built for this intrusion",
      "threadId": "F4Lo07Ls2uXZHq9pHEH73",
      "x": 90,
      "y": 980,
      "createdAt": "2026-07-08T23:26:23.725Z",
      "derivedFrom": "O1EZzp-7ROLVuI10h51tp",
      "stale": {
        "kind": "undermined",
        "causeEventId": "0EIpRV_pN1I_enRyiSfuF"
      },
      "type": "evidence",
      "sourceReliability": "B",
      "infoCredibility": 3
    },
    {
      "id": "OaxvsgY48sfxSCLBHLvwf",
      "text": "Who had physical access to the build server?",
      "x": 1040,
      "y": 60,
      "createdAt": "2026-07-08T23:31:05.725Z",
      "stale": {
        "kind": "fresh"
      },
      "type": "question",
      "threadId": "OaxvsgY48sfxSCLBHLvwf",
      "status": "open",
      "mutuallyExclusive": false,
      "parentThreadId": "F4Lo07Ls2uXZHq9pHEH73",
      "priority": "high"
    },
    {
      "id": "o0V81_wVv3JjXJfyj34re",
      "text": "Intrusion at ACME — June 2026",
      "x": 420,
      "y": 40,
      "createdAt": "2026-07-08T23:33:26.725Z",
      "stale": {
        "kind": "fresh"
      },
      "type": "incident",
      "threadId": "o0V81_wVv3JjXJfyj34re",
      "status": "open"
    },
    {
      "id": "vFw5lYGhOS0vOJsWAG4jZ",
      "text": "KESTREL loader executed on FIN-WS-041",
      "x": 380,
      "y": 240,
      "createdAt": "2026-07-08T23:38:08.725Z",
      "stale": {
        "kind": "fresh"
      },
      "type": "diamond_event",
      "threadId": "o0V81_wVv3JjXJfyj34re",
      "phase": "exploitation",
      "result": "success",
      "direction": "infrastructure_to_victim",
      "occurredAt": "2026-06-09"
    },
    {
      "id": "zXQvwOk0uFRmHDPKQcJQu",
      "text": "Finance-themed phishing lure delivered to 41 staff",
      "x": 80,
      "y": 240,
      "createdAt": "2026-07-08T23:34:13.725Z",
      "stale": {
        "kind": "fresh"
      },
      "type": "diamond_event",
      "threadId": "o0V81_wVv3JjXJfyj34re",
      "phase": "delivery",
      "result": "success",
      "direction": "infrastructure_to_victim",
      "occurredAt": "2026-06-09"
    },
    {
      "id": "_xh2PpXsbBFz5zEu6_rPP",
      "text": "Unattributed — tracked as UNC-ACME",
      "x": 680,
      "y": 60,
      "createdAt": "2026-07-08T23:50:40.725Z",
      "stale": {
        "kind": "fresh"
      },
      "type": "adversary",
      "threadId": "o0V81_wVv3JjXJfyj34re",
      "confidence": "low"
    },
    {
      "id": "2QGmwgq7dNoofVc9uR5ze",
      "text": "Beaconing to bulletproof host 45.155.87.12",
      "x": 680,
      "y": 240,
      "createdAt": "2026-07-08T23:42:03.725Z",
      "stale": {
        "kind": "fresh"
      },
      "type": "diamond_event",
      "threadId": "o0V81_wVv3JjXJfyj34re",
      "phase": "command_and_control",
      "result": "success",
      "direction": "bidirectional",
      "occurredAt": "2026-06-10"
    },
    {
      "id": "AvMWn9f1NWbopONzwkucL",
      "text": "Bulletproof host 45.155.87.12 (C2)",
      "x": 760,
      "y": 460,
      "createdAt": "2026-07-08T23:55:22.725Z",
      "stale": {
        "kind": "fresh"
      },
      "type": "infrastructure",
      "threadId": "o0V81_wVv3JjXJfyj34re",
      "confidence": "high"
    },
    {
      "id": "JZCFeln-RZWg65zNpA8d6",
      "text": "KESTREL loader (custom build)",
      "x": 300,
      "y": 460,
      "createdAt": "2026-07-08T23:52:14.725Z",
      "stale": {
        "kind": "fresh"
      },
      "type": "capability",
      "threadId": "o0V81_wVv3JjXJfyj34re",
      "confidence": "moderate"
    },
    {
      "id": "MSVV96HWDyZKFGz_pQyu5",
      "text": "Staged archive exfiltrated over HTTPS",
      "x": 980,
      "y": 240,
      "createdAt": "2026-07-08T23:45:58.725Z",
      "stale": {
        "kind": "fresh"
      },
      "type": "diamond_event",
      "threadId": "o0V81_wVv3JjXJfyj34re",
      "phase": "actions_on_objectives",
      "result": "success",
      "direction": "victim_to_infrastructure",
      "occurredAt": "2026-06-11"
    },
    {
      "id": "XhJVHGWTcSHZYdLOsqPtb",
      "text": "Spear-phish lure, finance theme",
      "x": 60,
      "y": 460,
      "createdAt": "2026-07-08T23:53:48.725Z",
      "stale": {
        "kind": "fresh"
      },
      "type": "capability",
      "threadId": "o0V81_wVv3JjXJfyj34re",
      "confidence": "moderate"
    },
    {
      "id": "YD-1w7WZ5XduZIk8lYmtS",
      "text": "RDP login from dormant service account",
      "x": 1280,
      "y": 240,
      "createdAt": "2026-07-08T23:49:53.725Z",
      "stale": {
        "kind": "fresh"
      },
      "type": "diamond_event",
      "threadId": "o0V81_wVv3JjXJfyj34re"
    },
    {
      "id": "A93mgK01wEWMR_dKhC2Ya",
      "text": "ACME finance workstation FIN-WS-041",
      "x": 500,
      "y": 620,
      "createdAt": "2026-07-08T23:56:56.725Z",
      "stale": {
        "kind": "fresh"
      },
      "type": "victim",
      "threadId": "o0V81_wVv3JjXJfyj34re",
      "confidence": "high"
    },
    {
      "id": "SuvFj9DYwiRofOoIVN9LZ",
      "text": "Passive DNS ties 45.155.87.12 to a 2024 APT-Q campaign",
      "x": 700,
      "y": 800,
      "createdAt": "2026-07-09T00:07:07.725Z",
      "stale": {
        "kind": "fresh"
      },
      "type": "evidence",
      "threadId": "o0V81_wVv3JjXJfyj34re",
      "sourceReliability": "C",
      "infoCredibility": 3
    },
    {
      "id": "TKS4wNrTpCWKTqM8PzbV5",
      "text": "Mail gateway logs: 41 lure deliveries, 3 clicks",
      "x": 60,
      "y": 800,
      "createdAt": "2026-07-09T00:04:46.725Z",
      "stale": {
        "kind": "fresh"
      },
      "type": "evidence",
      "threadId": "o0V81_wVv3JjXJfyj34re",
      "sourceReliability": "B",
      "infoCredibility": 2
    },
    {
      "id": "4SKTl_F8rO43KM2f-ekhG",
      "text": "Initial access was via the finance-themed phishing wave",
      "x": 1280,
      "y": 620,
      "createdAt": "2026-07-09T00:14:10.725Z",
      "stale": {
        "kind": "fresh"
      },
      "type": "claim",
      "threadId": "o0V81_wVv3JjXJfyj34re",
      "status": "open",
      "likelihood": "likely",
      "confidence": "moderate"
    },
    {
      "id": "TNfNsv_AzGq-_SRR1lY5M",
      "text": "Host serves dozens of unrelated bulletproof clients",
      "x": 1000,
      "y": 800,
      "createdAt": "2026-07-09T00:09:28.725Z",
      "stale": {
        "kind": "fresh"
      },
      "type": "evidence",
      "threadId": "o0V81_wVv3JjXJfyj34re",
      "sourceReliability": "C",
      "infoCredibility": 3
    }
  ],
  "edges": [
    {
      "id": "2AGX6yzu5Bny-o8lm-U_w",
      "type": "answers",
      "from": "JUgKHcme2oRbzU-6FZZe2",
      "to": "F4Lo07Ls2uXZHq9pHEH73",
      "createdAt": "2026-07-08T22:26:51.725Z"
    },
    {
      "id": "Js7MrHGR240gbWOHyGj8D",
      "type": "answers",
      "from": "J59lyA1PwKWOgP0p9AQc0",
      "to": "F4Lo07Ls2uXZHq9pHEH73",
      "createdAt": "2026-07-08T22:25:17.725Z"
    },
    {
      "id": "KoKLtQ8Hs3ONX6XEKgrWX",
      "type": "answers",
      "from": "1kMNXyC-mMe4Z_tyEK9hz",
      "to": "F4Lo07Ls2uXZHq9pHEH73",
      "createdAt": "2026-07-08T22:26:04.725Z"
    },
    {
      "id": "gn1gGBMyC6yytu_FBztp3",
      "type": "rests_on",
      "from": "J59lyA1PwKWOgP0p9AQc0",
      "to": "QjWh6X0AYPGX8p-I2CgFF",
      "createdAt": "2026-07-08T22:37:02.725Z"
    },
    {
      "id": "qps-b4rEal5yPSO_o2qpk",
      "type": "rests_on",
      "from": "J59lyA1PwKWOgP0p9AQc0",
      "to": "Lm-7BtyHi0xd-0byWGxG2",
      "createdAt": "2026-07-08T22:36:15.725Z"
    },
    {
      "id": "i-9u5T4B-fc63QirbgqtZ",
      "type": "rests_on",
      "from": "JUgKHcme2oRbzU-6FZZe2",
      "to": "GeiY5JM8dUvdaZb8Z6q9r",
      "createdAt": "2026-07-08T22:37:49.725Z"
    },
    {
      "id": "jqmjXC_rRnf9lTM3qEfum",
      "type": "rests_on",
      "from": "JUgKHcme2oRbzU-6FZZe2",
      "to": "Goz2EzUOhdS4E-KfxNRVL",
      "createdAt": "2026-07-08T22:38:36.725Z"
    },
    {
      "id": "MbQyx8x-uJjqUYrgbsGCU",
      "type": "consistent_with",
      "from": "wKdNsTR7D9Nqa3Uj0umEF",
      "to": "J59lyA1PwKWOgP0p9AQc0",
      "createdAt": "2026-07-08T22:58:11.725Z"
    },
    {
      "id": "fivKqBST17wgrkATGIR1u",
      "type": "consistent_with",
      "from": "lOcH6_eyof6KJOU2Wl6xv",
      "to": "JUgKHcme2oRbzU-6FZZe2",
      "createdAt": "2026-07-08T23:03:40.725Z"
    },
    {
      "id": "lgxfC9n6y-rUqJuhdcpZQ",
      "type": "consistent_with",
      "from": "DKKqs5O4yDwEaaS5aNSnY",
      "to": "J59lyA1PwKWOgP0p9AQc0",
      "createdAt": "2026-07-08T23:00:32.725Z"
    },
    {
      "id": "m-rXCK6wbyCE5cYMgAhy8",
      "type": "inconsistent_with",
      "from": "DKKqs5O4yDwEaaS5aNSnY",
      "to": "JUgKHcme2oRbzU-6FZZe2",
      "createdAt": "2026-07-08T23:01:19.725Z"
    },
    {
      "id": "N3iC34Kb9R77mly7UccTD",
      "type": "inconsistent_with",
      "from": "wKdNsTR7D9Nqa3Uj0umEF",
      "to": "JUgKHcme2oRbzU-6FZZe2",
      "createdAt": "2026-07-08T22:59:45.725Z"
    },
    {
      "id": "o8ex-f6A3VFCZdxxsQHrK",
      "type": "consistent_with",
      "from": "wKdNsTR7D9Nqa3Uj0umEF",
      "to": "1kMNXyC-mMe4Z_tyEK9hz",
      "createdAt": "2026-07-08T22:58:58.725Z"
    },
    {
      "id": "Ou-dWe6TX-bH2n_P48l22",
      "type": "consistent_with",
      "from": "lOcH6_eyof6KJOU2Wl6xv",
      "to": "J59lyA1PwKWOgP0p9AQc0",
      "createdAt": "2026-07-08T23:02:06.725Z"
    },
    {
      "id": "UpEKFhn1RpcT4eDcaSKQe",
      "type": "consistent_with",
      "from": "lOcH6_eyof6KJOU2Wl6xv",
      "to": "1kMNXyC-mMe4Z_tyEK9hz",
      "createdAt": "2026-07-08T23:02:53.725Z"
    },
    {
      "id": "cbwJDcRqsTSQ3V_sEYuBB",
      "type": "consistent_with",
      "from": "cNK0zJjA5FEzGP5fehN0b",
      "to": "JUgKHcme2oRbzU-6FZZe2",
      "createdAt": "2026-07-08T23:04:27.725Z"
    },
    {
      "id": "dHybtbANCeS9IycYb8jtC",
      "type": "consistent_with",
      "from": "iSShZhcofDGMCk7Fm2LQ3",
      "to": "JUgKHcme2oRbzU-6FZZe2",
      "createdAt": "2026-07-08T23:09:56.725Z"
    },
    {
      "id": "GxdnPdoYuRvG8j251vwwn",
      "type": "consistent_with",
      "from": "jL_3WrN01R7_5DcN2VPGH",
      "to": "JUgKHcme2oRbzU-6FZZe2",
      "createdAt": "2026-07-08T23:06:01.725Z"
    },
    {
      "id": "rkN3e62KJAXhB80GX6BUT",
      "type": "consistent_with",
      "from": "BEoS8RZFx2E1I2qk0d5f2",
      "to": "1kMNXyC-mMe4Z_tyEK9hz",
      "createdAt": "2026-07-08T23:07:35.725Z"
    },
    {
      "id": "T_jy3-adCAiYj9pXU-dEl",
      "type": "consistent_with",
      "from": "jL_3WrN01R7_5DcN2VPGH",
      "to": "1kMNXyC-mMe4Z_tyEK9hz",
      "createdAt": "2026-07-08T23:06:48.725Z"
    },
    {
      "id": "VcCg3ZhAmCroaUh1Hm8G3",
      "type": "consistent_with",
      "from": "6EmdJnCl1l0_vF4SP40IG",
      "to": "1kMNXyC-mMe4Z_tyEK9hz",
      "createdAt": "2026-07-08T23:08:22.725Z"
    },
    {
      "id": "YC74rl1Gn7wD0mtCZoYLt",
      "type": "inconsistent_with",
      "from": "6EmdJnCl1l0_vF4SP40IG",
      "to": "J59lyA1PwKWOgP0p9AQc0",
      "createdAt": "2026-07-08T23:09:09.725Z"
    },
    {
      "id": "ZuBzrlqvkCL9ulheLBgtf",
      "type": "inconsistent_with",
      "from": "cNK0zJjA5FEzGP5fehN0b",
      "to": "J59lyA1PwKWOgP0p9AQc0",
      "createdAt": "2026-07-08T23:05:14.725Z"
    },
    {
      "id": "WtlGViGp79DcWLhbvfZGo",
      "type": "answers",
      "from": "O1EZzp-7ROLVuI10h51tp",
      "to": "edWnPwcXCSAfJnQc_cb6G",
      "createdAt": "2026-07-08T23:18:33.725Z"
    },
    {
      "id": "8xukSGrlZf1pW_lCbDlWO",
      "type": "answers",
      "from": "kFKpiOCof28uB0RWmoYL3",
      "to": "edWnPwcXCSAfJnQc_cb6G",
      "createdAt": "2026-07-08T23:19:20.725Z"
    },
    {
      "id": "BJWp1REnhV8Actu4xwkDi",
      "type": "consistent_with",
      "from": "X6Ws-hHkbBG7POvuE4mEL",
      "to": "O1EZzp-7ROLVuI10h51tp",
      "createdAt": "2026-07-08T23:22:28.725Z"
    },
    {
      "id": "Cw5bHlRARlf7TK-PdVmBm",
      "type": "inconsistent_with",
      "from": "X6Ws-hHkbBG7POvuE4mEL",
      "to": "kFKpiOCof28uB0RWmoYL3",
      "createdAt": "2026-07-08T23:23:15.725Z"
    },
    {
      "id": "OBji7M3OiGq5G7bZf4WuT",
      "type": "consistent_with",
      "from": "FyQcj2ky8tpl1dautOBRY",
      "to": "J59lyA1PwKWOgP0p9AQc0",
      "createdAt": "2026-07-08T23:28:44.725Z"
    },
    {
      "id": "_IS6bhk-mny78LrTNp0g6",
      "type": "characterizes",
      "from": "A93mgK01wEWMR_dKhC2Ya",
      "to": "zXQvwOk0uFRmHDPKQcJQu",
      "createdAt": "2026-07-08T23:59:17.725Z"
    },
    {
      "id": "-b9yjmwG9mdHR8ahI9OU5",
      "type": "characterizes",
      "from": "JZCFeln-RZWg65zNpA8d6",
      "to": "vFw5lYGhOS0vOJsWAG4jZ",
      "createdAt": "2026-07-09T00:00:04.725Z"
    },
    {
      "id": "k1FcjCzksqI1xqAKxqnjk",
      "type": "characterizes",
      "from": "XhJVHGWTcSHZYdLOsqPtb",
      "to": "zXQvwOk0uFRmHDPKQcJQu",
      "createdAt": "2026-07-08T23:58:30.725Z"
    },
    {
      "id": "2MbK0XhzX2S22oq4PfU3R",
      "type": "characterizes",
      "from": "_xh2PpXsbBFz5zEu6_rPP",
      "to": "2QGmwgq7dNoofVc9uR5ze",
      "createdAt": "2026-07-09T00:01:38.725Z"
    },
    {
      "id": "97huz7CRVDWA8rgnnxqsz",
      "type": "characterizes",
      "from": "AvMWn9f1NWbopONzwkucL",
      "to": "2QGmwgq7dNoofVc9uR5ze",
      "createdAt": "2026-07-09T00:02:25.725Z"
    },
    {
      "id": "dOXWXf4kca0A2mtmnFYYC",
      "type": "characterizes",
      "from": "AvMWn9f1NWbopONzwkucL",
      "to": "MSVV96HWDyZKFGz_pQyu5",
      "createdAt": "2026-07-09T00:03:12.725Z"
    },
    {
      "id": "Gt0vI0-zPMUwShdQQT4vR",
      "type": "characterizes",
      "from": "A93mgK01wEWMR_dKhC2Ya",
      "to": "vFw5lYGhOS0vOJsWAG4jZ",
      "createdAt": "2026-07-09T00:00:51.725Z"
    },
    {
      "id": "smZPjHRqMujBTxIbOdlSN",
      "type": "characterizes",
      "from": "A93mgK01wEWMR_dKhC2Ya",
      "to": "MSVV96HWDyZKFGz_pQyu5",
      "createdAt": "2026-07-09T00:03:59.725Z"
    },
    {
      "id": "_VHZteb0-OBq0pEx1Kazz",
      "type": "consistent_with",
      "from": "TKS4wNrTpCWKTqM8PzbV5",
      "to": "XhJVHGWTcSHZYdLOsqPtb",
      "createdAt": "2026-07-09T00:11:49.725Z"
    },
    {
      "id": "3n2CpdsEXcMOR_Ss_GOW7",
      "type": "answers",
      "from": "4SKTl_F8rO43KM2f-ekhG",
      "to": "o0V81_wVv3JjXJfyj34re",
      "createdAt": "2026-07-09T00:16:31.725Z"
    },
    {
      "id": "Q_SRnbdvNBViLtBxzYzVs",
      "type": "inconsistent_with",
      "from": "TNfNsv_AzGq-_SRR1lY5M",
      "to": "_xh2PpXsbBFz5zEu6_rPP",
      "createdAt": "2026-07-09T00:13:23.725Z"
    },
    {
      "id": "TcWweRiFwDYmbvT05_V8K",
      "type": "consistent_with",
      "from": "SuvFj9DYwiRofOoIVN9LZ",
      "to": "AvMWn9f1NWbopONzwkucL",
      "createdAt": "2026-07-09T00:12:36.725Z"
    }
  ],
  "events": [
    {
      "id": "EROYOLuJB5iMr9A58n9Br",
      "seq": 0,
      "at": "2026-07-06T22:25:17.725Z",
      "type": "thread_created",
      "payload": {
        "rootQuestionId": "F4Lo07Ls2uXZHq9pHEH73",
        "parentThreadId": null
      },
      "nodeId": "F4Lo07Ls2uXZHq9pHEH73",
      "threadId": "F4Lo07Ls2uXZHq9pHEH73"
    },
    {
      "id": "8HgAr9U8dvYEZUZPoVRSb",
      "seq": 1,
      "at": "2026-07-06T22:26:04.725Z",
      "type": "node_created",
      "payload": {
        "node": {
          "id": "F4Lo07Ls2uXZHq9pHEH73",
          "text": "Is APT-Q responsible for the intrusion at ACME?",
          "x": 420,
          "y": 40,
          "createdAt": "2026-07-06T22:26:04.725Z",
          "stale": {
            "kind": "fresh"
          },
          "type": "question",
          "threadId": "F4Lo07Ls2uXZHq9pHEH73",
          "status": "open",
          "mutuallyExclusive": false
        },
        "captureMs": 7000
      },
      "nodeId": "F4Lo07Ls2uXZHq9pHEH73",
      "threadId": "F4Lo07Ls2uXZHq9pHEH73"
    },
    {
      "id": "hZ_bL2PHX54wt3Ysrx9UO",
      "seq": 2,
      "at": "2026-07-06T22:26:51.725Z",
      "type": "judgement_declared",
      "payload": {
        "field": "mutuallyExclusive",
        "before": false,
        "after": true
      },
      "nodeId": "F4Lo07Ls2uXZHq9pHEH73",
      "threadId": "F4Lo07Ls2uXZHq9pHEH73"
    },
    {
      "id": "RI047i89oL5bq9k2-n2I5",
      "seq": 3,
      "at": "2026-07-06T22:27:38.725Z",
      "type": "node_created",
      "payload": {
        "node": {
          "id": "J59lyA1PwKWOgP0p9AQc0",
          "text": "APT-Q conducted the intrusion",
          "x": 140,
          "y": 230,
          "createdAt": "2026-07-06T22:27:38.725Z",
          "stale": {
            "kind": "fresh"
          },
          "type": "claim",
          "threadId": "F4Lo07Ls2uXZHq9pHEH73",
          "status": "open"
        },
        "captureMs": 5000
      },
      "nodeId": "J59lyA1PwKWOgP0p9AQc0",
      "threadId": "F4Lo07Ls2uXZHq9pHEH73"
    },
    {
      "id": "H0TTnpn5JxSBZKTv8EL9A",
      "seq": 4,
      "at": "2026-07-06T22:28:25.725Z",
      "type": "judgement_declared",
      "payload": {
        "field": "likelihood",
        "before": null,
        "after": "likely"
      },
      "nodeId": "J59lyA1PwKWOgP0p9AQc0",
      "threadId": "F4Lo07Ls2uXZHq9pHEH73"
    },
    {
      "id": "eA0guwIINo-Pe1zBihZ6b",
      "seq": 5,
      "at": "2026-07-06T22:29:12.725Z",
      "type": "judgement_declared",
      "payload": {
        "field": "confidence",
        "before": null,
        "after": "moderate"
      },
      "nodeId": "J59lyA1PwKWOgP0p9AQc0",
      "threadId": "F4Lo07Ls2uXZHq9pHEH73"
    },
    {
      "id": "C8c9NT5mjD90YT05bmgxl",
      "seq": 6,
      "at": "2026-07-06T22:29:59.725Z",
      "type": "node_created",
      "payload": {
        "node": {
          "id": "1kMNXyC-mMe4Z_tyEK9hz",
          "text": "A criminal affiliate reused APT-Q tooling",
          "x": 430,
          "y": 230,
          "createdAt": "2026-07-06T22:29:59.725Z",
          "stale": {
            "kind": "fresh"
          },
          "type": "claim",
          "threadId": "F4Lo07Ls2uXZHq9pHEH73",
          "status": "open"
        },
        "captureMs": 6000
      },
      "nodeId": "1kMNXyC-mMe4Z_tyEK9hz",
      "threadId": "F4Lo07Ls2uXZHq9pHEH73"
    },
    {
      "id": "zO-B2Wmlb2zQjth3RtrYs",
      "seq": 7,
      "at": "2026-07-06T22:30:46.725Z",
      "type": "judgement_declared",
      "payload": {
        "field": "likelihood",
        "before": null,
        "after": "realistic_possibility"
      },
      "nodeId": "1kMNXyC-mMe4Z_tyEK9hz",
      "threadId": "F4Lo07Ls2uXZHq9pHEH73"
    },
    {
      "id": "5UjIjWxYrPNinblB0UgUl",
      "seq": 8,
      "at": "2026-07-06T22:31:33.725Z",
      "type": "judgement_declared",
      "payload": {
        "field": "confidence",
        "before": null,
        "after": "low"
      },
      "nodeId": "1kMNXyC-mMe4Z_tyEK9hz",
      "threadId": "F4Lo07Ls2uXZHq9pHEH73"
    },
    {
      "id": "UnnP4StzixbtJojoGc0rj",
      "seq": 9,
      "at": "2026-07-06T22:32:20.725Z",
      "type": "node_created",
      "payload": {
        "node": {
          "id": "JUgKHcme2oRbzU-6FZZe2",
          "text": "An insider staged the intrusion to look external",
          "x": 720,
          "y": 230,
          "createdAt": "2026-07-06T22:32:20.725Z",
          "stale": {
            "kind": "fresh"
          },
          "type": "claim",
          "threadId": "F4Lo07Ls2uXZHq9pHEH73",
          "status": "open"
        },
        "captureMs": 7000
      },
      "nodeId": "JUgKHcme2oRbzU-6FZZe2",
      "threadId": "F4Lo07Ls2uXZHq9pHEH73"
    },
    {
      "id": "a-ZstJaGbREcwakk64GLP",
      "seq": 10,
      "at": "2026-07-06T22:33:07.725Z",
      "type": "judgement_declared",
      "payload": {
        "field": "likelihood",
        "before": null,
        "after": "unlikely"
      },
      "nodeId": "JUgKHcme2oRbzU-6FZZe2",
      "threadId": "F4Lo07Ls2uXZHq9pHEH73"
    },
    {
      "id": "rl8YpUV5Dl6u-sPtUE6pb",
      "seq": 11,
      "at": "2026-07-06T22:33:54.725Z",
      "type": "judgement_declared",
      "payload": {
        "field": "confidence",
        "before": null,
        "after": "low"
      },
      "nodeId": "JUgKHcme2oRbzU-6FZZe2",
      "threadId": "F4Lo07Ls2uXZHq9pHEH73"
    },
    {
      "id": "29gGzwP3CO7GNk9G586zz",
      "seq": 12,
      "at": "2026-07-08T22:25:17.725Z",
      "type": "edge_created",
      "payload": {
        "edge": {
          "id": "Js7MrHGR240gbWOHyGj8D",
          "type": "answers",
          "from": "J59lyA1PwKWOgP0p9AQc0",
          "to": "F4Lo07Ls2uXZHq9pHEH73",
          "createdAt": "2026-07-08T22:25:17.725Z"
        }
      },
      "edgeId": "Js7MrHGR240gbWOHyGj8D",
      "threadId": "F4Lo07Ls2uXZHq9pHEH73"
    },
    {
      "id": "lvkr-scSfgA2Kn51Wq4Ke",
      "seq": 13,
      "at": "2026-07-08T22:26:04.725Z",
      "type": "edge_created",
      "payload": {
        "edge": {
          "id": "KoKLtQ8Hs3ONX6XEKgrWX",
          "type": "answers",
          "from": "1kMNXyC-mMe4Z_tyEK9hz",
          "to": "F4Lo07Ls2uXZHq9pHEH73",
          "createdAt": "2026-07-08T22:26:04.725Z"
        }
      },
      "edgeId": "KoKLtQ8Hs3ONX6XEKgrWX",
      "threadId": "F4Lo07Ls2uXZHq9pHEH73"
    },
    {
      "id": "G4OZ0kuiJcnnoa3Hrx-6C",
      "seq": 14,
      "at": "2026-07-08T22:26:51.725Z",
      "type": "edge_created",
      "payload": {
        "edge": {
          "id": "2AGX6yzu5Bny-o8lm-U_w",
          "type": "answers",
          "from": "JUgKHcme2oRbzU-6FZZe2",
          "to": "F4Lo07Ls2uXZHq9pHEH73",
          "createdAt": "2026-07-08T22:26:51.725Z"
        }
      },
      "edgeId": "2AGX6yzu5Bny-o8lm-U_w",
      "threadId": "F4Lo07Ls2uXZHq9pHEH73"
    },
    {
      "id": "EpqJSpnqbnYF1LRrtKdGQ",
      "seq": 15,
      "at": "2026-07-08T22:27:38.725Z",
      "type": "node_created",
      "payload": {
        "node": {
          "id": "Lm-7BtyHi0xd-0byWGxG2",
          "text": "Code overlap implies common authorship",
          "x": 60,
          "y": 430,
          "createdAt": "2026-07-08T22:27:38.725Z",
          "stale": {
            "kind": "fresh"
          },
          "type": "assumption",
          "threadId": "F4Lo07Ls2uXZHq9pHEH73",
          "linchpin": false
        },
        "captureMs": 3000
      },
      "nodeId": "Lm-7BtyHi0xd-0byWGxG2",
      "threadId": "F4Lo07Ls2uXZHq9pHEH73"
    },
    {
      "id": "7j1pXg5Dn9DpWdayjZ9m5",
      "seq": 16,
      "at": "2026-07-08T22:28:25.725Z",
      "type": "judgement_declared",
      "payload": {
        "field": "validity",
        "before": null,
        "after": "caveated"
      },
      "nodeId": "Lm-7BtyHi0xd-0byWGxG2",
      "threadId": "F4Lo07Ls2uXZHq9pHEH73"
    },
    {
      "id": "LSNz2oVRkf12gJRBxnirq",
      "seq": 17,
      "at": "2026-07-08T22:29:12.725Z",
      "type": "judgement_declared",
      "payload": {
        "field": "linchpin",
        "before": false,
        "after": true
      },
      "nodeId": "Lm-7BtyHi0xd-0byWGxG2",
      "threadId": "F4Lo07Ls2uXZHq9pHEH73"
    },
    {
      "id": "L-c73pbjp1qKR9O0QjLvD",
      "seq": 18,
      "at": "2026-07-08T22:29:59.725Z",
      "type": "node_text_edited",
      "payload": {
        "field": "abandonTrigger",
        "before": null,
        "after": "KESTREL source or builder leaks publicly"
      },
      "nodeId": "Lm-7BtyHi0xd-0byWGxG2",
      "threadId": "F4Lo07Ls2uXZHq9pHEH73"
    },
    {
      "id": "Zup7Z7VAfXJgR47PHXWLO",
      "seq": 19,
      "at": "2026-07-08T22:30:46.725Z",
      "type": "node_created",
      "payload": {
        "node": {
          "id": "GeiY5JM8dUvdaZb8Z6q9r",
          "text": "ACME's VPN logs are complete and untampered",
          "x": 640,
          "y": 430,
          "createdAt": "2026-07-08T22:30:46.725Z",
          "stale": {
            "kind": "fresh"
          },
          "type": "assumption",
          "threadId": "F4Lo07Ls2uXZHq9pHEH73",
          "linchpin": false
        },
        "captureMs": 5000
      },
      "nodeId": "GeiY5JM8dUvdaZb8Z6q9r",
      "threadId": "F4Lo07Ls2uXZHq9pHEH73"
    },
    {
      "id": "TUzoC9nKKzX4j495qouPu",
      "seq": 20,
      "at": "2026-07-08T22:31:33.725Z",
      "type": "judgement_declared",
      "payload": {
        "field": "validity",
        "before": null,
        "after": "supported"
      },
      "nodeId": "GeiY5JM8dUvdaZb8Z6q9r",
      "threadId": "F4Lo07Ls2uXZHq9pHEH73"
    },
    {
      "id": "uR5bZWYQtIwedulmcakns",
      "seq": 21,
      "at": "2026-07-08T22:32:20.725Z",
      "type": "node_created",
      "payload": {
        "node": {
          "id": "Goz2EzUOhdS4E-KfxNRVL",
          "text": "Access implies intent",
          "x": 880,
          "y": 430,
          "createdAt": "2026-07-08T22:32:20.725Z",
          "stale": {
            "kind": "fresh"
          },
          "type": "assumption",
          "threadId": "F4Lo07Ls2uXZHq9pHEH73",
          "linchpin": false
        },
        "captureMs": 8000
      },
      "nodeId": "Goz2EzUOhdS4E-KfxNRVL",
      "threadId": "F4Lo07Ls2uXZHq9pHEH73"
    },
    {
      "id": "Q4EZi2RBQm8Tc1uxmll0E",
      "seq": 22,
      "at": "2026-07-08T22:33:07.725Z",
      "type": "judgement_declared",
      "payload": {
        "field": "validity",
        "before": null,
        "after": "unsupported"
      },
      "nodeId": "Goz2EzUOhdS4E-KfxNRVL",
      "threadId": "F4Lo07Ls2uXZHq9pHEH73"
    },
    {
      "id": "wGfZaA5g7D_IJmOUekocC",
      "seq": 23,
      "at": "2026-07-08T22:33:54.725Z",
      "type": "judgement_declared",
      "payload": {
        "field": "linchpin",
        "before": false,
        "after": true
      },
      "nodeId": "Goz2EzUOhdS4E-KfxNRVL",
      "threadId": "F4Lo07Ls2uXZHq9pHEH73"
    },
    {
      "id": "-BbVoEboDapzyBUOmF6hm",
      "seq": 24,
      "at": "2026-07-08T22:34:41.725Z",
      "type": "node_created",
      "payload": {
        "node": {
          "id": "QjWh6X0AYPGX8p-I2CgFF",
          "text": "APT-Q does not share infrastructure with affiliates",
          "x": 300,
          "y": 430,
          "createdAt": "2026-07-08T22:34:41.725Z",
          "stale": {
            "kind": "fresh"
          },
          "type": "assumption",
          "threadId": "F4Lo07Ls2uXZHq9pHEH73",
          "linchpin": false
        },
        "captureMs": 6000
      },
      "nodeId": "QjWh6X0AYPGX8p-I2CgFF",
      "threadId": "F4Lo07Ls2uXZHq9pHEH73"
    },
    {
      "id": "72vVhbPqQ-pxLBX9NZiwo",
      "seq": 25,
      "at": "2026-07-08T22:35:28.725Z",
      "type": "judgement_declared",
      "payload": {
        "field": "validity",
        "before": null,
        "after": "caveated"
      },
      "nodeId": "QjWh6X0AYPGX8p-I2CgFF",
      "threadId": "F4Lo07Ls2uXZHq9pHEH73"
    },
    {
      "id": "QmWt3utPervR9MOUdtiak",
      "seq": 26,
      "at": "2026-07-08T22:36:15.725Z",
      "type": "edge_created",
      "payload": {
        "edge": {
          "id": "qps-b4rEal5yPSO_o2qpk",
          "type": "rests_on",
          "from": "J59lyA1PwKWOgP0p9AQc0",
          "to": "Lm-7BtyHi0xd-0byWGxG2",
          "createdAt": "2026-07-08T22:36:15.725Z"
        }
      },
      "edgeId": "qps-b4rEal5yPSO_o2qpk",
      "threadId": "F4Lo07Ls2uXZHq9pHEH73"
    },
    {
      "id": "T15mpBKCpXhdv3eeAfcf3",
      "seq": 27,
      "at": "2026-07-08T22:37:02.725Z",
      "type": "edge_created",
      "payload": {
        "edge": {
          "id": "gn1gGBMyC6yytu_FBztp3",
          "type": "rests_on",
          "from": "J59lyA1PwKWOgP0p9AQc0",
          "to": "QjWh6X0AYPGX8p-I2CgFF",
          "createdAt": "2026-07-08T22:37:02.725Z"
        }
      },
      "edgeId": "gn1gGBMyC6yytu_FBztp3",
      "threadId": "F4Lo07Ls2uXZHq9pHEH73"
    },
    {
      "id": "NLp02_yh958BdMCi8R5vU",
      "seq": 28,
      "at": "2026-07-08T22:37:49.725Z",
      "type": "edge_created",
      "payload": {
        "edge": {
          "id": "i-9u5T4B-fc63QirbgqtZ",
          "type": "rests_on",
          "from": "JUgKHcme2oRbzU-6FZZe2",
          "to": "GeiY5JM8dUvdaZb8Z6q9r",
          "createdAt": "2026-07-08T22:37:49.725Z"
        }
      },
      "edgeId": "i-9u5T4B-fc63QirbgqtZ",
      "threadId": "F4Lo07Ls2uXZHq9pHEH73"
    },
    {
      "id": "s6P-VbS6VxPzeFjApud4W",
      "seq": 29,
      "at": "2026-07-08T22:38:36.725Z",
      "type": "edge_created",
      "payload": {
        "edge": {
          "id": "jqmjXC_rRnf9lTM3qEfum",
          "type": "rests_on",
          "from": "JUgKHcme2oRbzU-6FZZe2",
          "to": "Goz2EzUOhdS4E-KfxNRVL",
          "createdAt": "2026-07-08T22:38:36.725Z"
        }
      },
      "edgeId": "jqmjXC_rRnf9lTM3qEfum",
      "threadId": "F4Lo07Ls2uXZHq9pHEH73"
    },
    {
      "id": "J-JBshAwNBvBUkZZeJOs6",
      "seq": 30,
      "at": "2026-07-08T22:39:23.725Z",
      "type": "node_created",
      "payload": {
        "node": {
          "id": "wKdNsTR7D9Nqa3Uj0umEF",
          "text": "Loader shares code with APT-Q's KESTREL implant",
          "x": 80,
          "y": 640,
          "createdAt": "2026-07-08T22:39:23.725Z",
          "stale": {
            "kind": "fresh"
          },
          "type": "claim",
          "threadId": "F4Lo07Ls2uXZHq9pHEH73",
          "status": "open"
        },
        "captureMs": 5000
      },
      "nodeId": "wKdNsTR7D9Nqa3Uj0umEF",
      "threadId": "F4Lo07Ls2uXZHq9pHEH73"
    },
    {
      "id": "PysJsECFBIziKcx1Vfd6a",
      "seq": 31,
      "at": "2026-07-08T22:40:10.725Z",
      "type": "node_retyped",
      "payload": {
        "before": {
          "type": "claim",
          "judgements": {
            "status": "open"
          }
        },
        "after": {
          "type": "evidence"
        }
      },
      "nodeId": "wKdNsTR7D9Nqa3Uj0umEF",
      "threadId": "F4Lo07Ls2uXZHq9pHEH73"
    },
    {
      "id": "NimA2UNK1aV06QEHTiEpz",
      "seq": 32,
      "at": "2026-07-08T22:40:57.725Z",
      "type": "judgement_declared",
      "payload": {
        "field": "sourceReliability",
        "before": null,
        "after": "B"
      },
      "nodeId": "wKdNsTR7D9Nqa3Uj0umEF",
      "threadId": "F4Lo07Ls2uXZHq9pHEH73"
    },
    {
      "id": "mxaa_ZNfI6BBUTnpqOmyF",
      "seq": 33,
      "at": "2026-07-08T22:41:44.725Z",
      "type": "judgement_declared",
      "payload": {
        "field": "infoCredibility",
        "before": null,
        "after": 2
      },
      "nodeId": "wKdNsTR7D9Nqa3Uj0umEF",
      "threadId": "F4Lo07Ls2uXZHq9pHEH73"
    },
    {
      "id": "sElNGLFbs05JQtE8N82jq",
      "seq": 34,
      "at": "2026-07-08T22:42:31.725Z",
      "type": "node_created",
      "payload": {
        "node": {
          "id": "DKKqs5O4yDwEaaS5aNSnY",
          "text": "C2 infrastructure overlaps a 2024 APT-Q campaign",
          "x": 320,
          "y": 640,
          "createdAt": "2026-07-08T22:42:31.725Z",
          "stale": {
            "kind": "fresh"
          },
          "type": "evidence",
          "threadId": "F4Lo07Ls2uXZHq9pHEH73"
        },
        "captureMs": 8000
      },
      "nodeId": "DKKqs5O4yDwEaaS5aNSnY",
      "threadId": "F4Lo07Ls2uXZHq9pHEH73"
    },
    {
      "id": "QBhAooRVYQN4G7nzVSa2H",
      "seq": 35,
      "at": "2026-07-08T22:43:18.725Z",
      "type": "judgement_declared",
      "payload": {
        "field": "sourceReliability",
        "before": null,
        "after": "B"
      },
      "nodeId": "DKKqs5O4yDwEaaS5aNSnY",
      "threadId": "F4Lo07Ls2uXZHq9pHEH73"
    },
    {
      "id": "wJOthdT7nmJfmHvjH54GX",
      "seq": 36,
      "at": "2026-07-08T22:44:05.725Z",
      "type": "judgement_declared",
      "payload": {
        "field": "infoCredibility",
        "before": null,
        "after": 3
      },
      "nodeId": "DKKqs5O4yDwEaaS5aNSnY",
      "threadId": "F4Lo07Ls2uXZHq9pHEH73"
    },
    {
      "id": "8lolvII8eyFlkHBbncrd2",
      "seq": 37,
      "at": "2026-07-08T22:44:52.725Z",
      "type": "node_created",
      "payload": {
        "node": {
          "id": "lOcH6_eyof6KJOU2Wl6xv",
          "text": "Commodity credential-dumping tools used throughout",
          "x": 560,
          "y": 640,
          "createdAt": "2026-07-08T22:44:52.725Z",
          "stale": {
            "kind": "fresh"
          },
          "type": "evidence",
          "threadId": "F4Lo07Ls2uXZHq9pHEH73"
        },
        "captureMs": 4000
      },
      "nodeId": "lOcH6_eyof6KJOU2Wl6xv",
      "threadId": "F4Lo07Ls2uXZHq9pHEH73"
    },
    {
      "id": "rCp0qmWRLCt6DRUx76qc2",
      "seq": 38,
      "at": "2026-07-08T22:45:39.725Z",
      "type": "judgement_declared",
      "payload": {
        "field": "sourceReliability",
        "before": null,
        "after": "C"
      },
      "nodeId": "lOcH6_eyof6KJOU2Wl6xv",
      "threadId": "F4Lo07Ls2uXZHq9pHEH73"
    },
    {
      "id": "4sCeU7Ch6c45x2U7E6zmk",
      "seq": 39,
      "at": "2026-07-08T22:46:26.725Z",
      "type": "judgement_declared",
      "payload": {
        "field": "infoCredibility",
        "before": null,
        "after": 3
      },
      "nodeId": "lOcH6_eyof6KJOU2Wl6xv",
      "threadId": "F4Lo07Ls2uXZHq9pHEH73"
    },
    {
      "id": "ySHrsm9nIQqmu0oYKksdF",
      "seq": 40,
      "at": "2026-07-08T22:47:13.725Z",
      "type": "node_created",
      "payload": {
        "node": {
          "id": "cNK0zJjA5FEzGP5fehN0b",
          "text": "VPN logs show access from inside the HQ subnet",
          "x": 800,
          "y": 640,
          "createdAt": "2026-07-08T22:47:13.725Z",
          "stale": {
            "kind": "fresh"
          },
          "type": "evidence",
          "threadId": "F4Lo07Ls2uXZHq9pHEH73"
        },
        "captureMs": 7000
      },
      "nodeId": "cNK0zJjA5FEzGP5fehN0b",
      "threadId": "F4Lo07Ls2uXZHq9pHEH73"
    },
    {
      "id": "fodfO3GJlgv2RPoK-BrQR",
      "seq": 41,
      "at": "2026-07-08T22:48:00.725Z",
      "type": "judgement_declared",
      "payload": {
        "field": "sourceReliability",
        "before": null,
        "after": "D"
      },
      "nodeId": "cNK0zJjA5FEzGP5fehN0b",
      "threadId": "F4Lo07Ls2uXZHq9pHEH73"
    },
    {
      "id": "ojAvt1zWtx2ksl9RSxbEo",
      "seq": 42,
      "at": "2026-07-08T22:48:47.725Z",
      "type": "judgement_declared",
      "payload": {
        "field": "infoCredibility",
        "before": null,
        "after": 4
      },
      "nodeId": "cNK0zJjA5FEzGP5fehN0b",
      "threadId": "F4Lo07Ls2uXZHq9pHEH73"
    },
    {
      "id": "P_7kcGQD6o0bUlxnUj41y",
      "seq": 43,
      "at": "2026-07-08T22:49:34.725Z",
      "type": "node_created",
      "payload": {
        "node": {
          "id": "jL_3WrN01R7_5DcN2VPGH",
          "text": "Phishing lure written in fluent corporate English",
          "x": 1040,
          "y": 640,
          "createdAt": "2026-07-08T22:49:34.725Z",
          "stale": {
            "kind": "fresh"
          },
          "type": "evidence",
          "threadId": "F4Lo07Ls2uXZHq9pHEH73"
        },
        "captureMs": 3000
      },
      "nodeId": "jL_3WrN01R7_5DcN2VPGH",
      "threadId": "F4Lo07Ls2uXZHq9pHEH73"
    },
    {
      "id": "3y96N-UvVtcuRQxniB4eC",
      "seq": 44,
      "at": "2026-07-08T22:50:21.725Z",
      "type": "judgement_declared",
      "payload": {
        "field": "sourceReliability",
        "before": null,
        "after": "C"
      },
      "nodeId": "jL_3WrN01R7_5DcN2VPGH",
      "threadId": "F4Lo07Ls2uXZHq9pHEH73"
    },
    {
      "id": "Di_JUWhkln-6BBBYESUt9",
      "seq": 45,
      "at": "2026-07-08T22:51:08.725Z",
      "type": "judgement_declared",
      "payload": {
        "field": "infoCredibility",
        "before": null,
        "after": 3
      },
      "nodeId": "jL_3WrN01R7_5DcN2VPGH",
      "threadId": "F4Lo07Ls2uXZHq9pHEH73"
    },
    {
      "id": "VmfuC3aUsH_ueW28W74xR",
      "seq": 46,
      "at": "2026-07-08T22:51:55.725Z",
      "type": "node_created",
      "payload": {
        "node": {
          "id": "BEoS8RZFx2E1I2qk0d5f2",
          "text": "APT-Q is known to sell tooling to affiliates",
          "x": 200,
          "y": 800,
          "createdAt": "2026-07-08T22:51:55.725Z",
          "stale": {
            "kind": "fresh"
          },
          "type": "evidence",
          "threadId": "F4Lo07Ls2uXZHq9pHEH73"
        },
        "captureMs": 5000
      },
      "nodeId": "BEoS8RZFx2E1I2qk0d5f2",
      "threadId": "F4Lo07Ls2uXZHq9pHEH73"
    },
    {
      "id": "UYBaOQ74Ogn0shioJ2i77",
      "seq": 47,
      "at": "2026-07-08T22:52:42.725Z",
      "type": "judgement_declared",
      "payload": {
        "field": "sourceReliability",
        "before": null,
        "after": "B"
      },
      "nodeId": "BEoS8RZFx2E1I2qk0d5f2",
      "threadId": "F4Lo07Ls2uXZHq9pHEH73"
    },
    {
      "id": "Tp_erhlUV6kSdix9naCy2",
      "seq": 48,
      "at": "2026-07-08T22:53:29.725Z",
      "type": "judgement_declared",
      "payload": {
        "field": "infoCredibility",
        "before": null,
        "after": 2
      },
      "nodeId": "BEoS8RZFx2E1I2qk0d5f2",
      "threadId": "F4Lo07Ls2uXZHq9pHEH73"
    },
    {
      "id": "mCIMrg0ITkY41b2EEf-8z",
      "seq": 49,
      "at": "2026-07-08T22:54:16.725Z",
      "type": "node_created",
      "payload": {
        "node": {
          "id": "6EmdJnCl1l0_vF4SP40IG",
          "text": "Ransom note demands payment in Monero",
          "x": 460,
          "y": 800,
          "createdAt": "2026-07-08T22:54:16.725Z",
          "stale": {
            "kind": "fresh"
          },
          "type": "evidence",
          "threadId": "F4Lo07Ls2uXZHq9pHEH73"
        },
        "captureMs": 3000
      },
      "nodeId": "6EmdJnCl1l0_vF4SP40IG",
      "threadId": "F4Lo07Ls2uXZHq9pHEH73"
    },
    {
      "id": "ghXbz_KqP-TI1yn43Lbd1",
      "seq": 50,
      "at": "2026-07-08T22:55:03.725Z",
      "type": "judgement_declared",
      "payload": {
        "field": "sourceReliability",
        "before": null,
        "after": "C"
      },
      "nodeId": "6EmdJnCl1l0_vF4SP40IG",
      "threadId": "F4Lo07Ls2uXZHq9pHEH73"
    },
    {
      "id": "Gl5oRHeXQlrsjmzPuZbT4",
      "seq": 51,
      "at": "2026-07-08T22:55:50.725Z",
      "type": "judgement_declared",
      "payload": {
        "field": "infoCredibility",
        "before": null,
        "after": 2
      },
      "nodeId": "6EmdJnCl1l0_vF4SP40IG",
      "threadId": "F4Lo07Ls2uXZHq9pHEH73"
    },
    {
      "id": "SR_yZJ7CbfiX4srSpXPsD",
      "seq": 52,
      "at": "2026-07-08T22:56:37.725Z",
      "type": "node_created",
      "payload": {
        "node": {
          "id": "iSShZhcofDGMCk7Fm2LQ3",
          "text": "Forum chatter claims an insider sold ACME access",
          "x": 720,
          "y": 800,
          "createdAt": "2026-07-08T22:56:37.725Z",
          "stale": {
            "kind": "fresh"
          },
          "type": "evidence",
          "threadId": "F4Lo07Ls2uXZHq9pHEH73"
        },
        "captureMs": 8000
      },
      "nodeId": "iSShZhcofDGMCk7Fm2LQ3",
      "threadId": "F4Lo07Ls2uXZHq9pHEH73"
    },
    {
      "id": "d97jw_JVjnU42zuPdLfO8",
      "seq": 53,
      "at": "2026-07-08T22:57:24.725Z",
      "type": "node_text_edited",
      "payload": {
        "field": "sourceNote",
        "before": null,
        "after": "Single dark-web forum post, unverified"
      },
      "nodeId": "iSShZhcofDGMCk7Fm2LQ3",
      "threadId": "F4Lo07Ls2uXZHq9pHEH73"
    },
    {
      "id": "lTml_se2w-hhDzUvz7k5S",
      "seq": 54,
      "at": "2026-07-08T22:58:11.725Z",
      "type": "edge_created",
      "payload": {
        "edge": {
          "id": "MbQyx8x-uJjqUYrgbsGCU",
          "type": "consistent_with",
          "from": "wKdNsTR7D9Nqa3Uj0umEF",
          "to": "J59lyA1PwKWOgP0p9AQc0",
          "createdAt": "2026-07-08T22:58:11.725Z"
        }
      },
      "edgeId": "MbQyx8x-uJjqUYrgbsGCU",
      "threadId": "F4Lo07Ls2uXZHq9pHEH73"
    },
    {
      "id": "qau-EdrJCGflkb-izeAoz",
      "seq": 55,
      "at": "2026-07-08T22:58:58.725Z",
      "type": "edge_created",
      "payload": {
        "edge": {
          "id": "o8ex-f6A3VFCZdxxsQHrK",
          "type": "consistent_with",
          "from": "wKdNsTR7D9Nqa3Uj0umEF",
          "to": "1kMNXyC-mMe4Z_tyEK9hz",
          "createdAt": "2026-07-08T22:58:58.725Z"
        }
      },
      "edgeId": "o8ex-f6A3VFCZdxxsQHrK",
      "threadId": "F4Lo07Ls2uXZHq9pHEH73"
    },
    {
      "id": "2HvKgCGR5R1ieNmdRYjN4",
      "seq": 56,
      "at": "2026-07-08T22:59:45.725Z",
      "type": "edge_created",
      "payload": {
        "edge": {
          "id": "N3iC34Kb9R77mly7UccTD",
          "type": "inconsistent_with",
          "from": "wKdNsTR7D9Nqa3Uj0umEF",
          "to": "JUgKHcme2oRbzU-6FZZe2",
          "createdAt": "2026-07-08T22:59:45.725Z"
        }
      },
      "edgeId": "N3iC34Kb9R77mly7UccTD",
      "threadId": "F4Lo07Ls2uXZHq9pHEH73"
    },
    {
      "id": "hpHOq_j3fAK3U1b_W26MZ",
      "seq": 57,
      "at": "2026-07-08T23:00:32.725Z",
      "type": "edge_created",
      "payload": {
        "edge": {
          "id": "lgxfC9n6y-rUqJuhdcpZQ",
          "type": "consistent_with",
          "from": "DKKqs5O4yDwEaaS5aNSnY",
          "to": "J59lyA1PwKWOgP0p9AQc0",
          "createdAt": "2026-07-08T23:00:32.725Z"
        }
      },
      "edgeId": "lgxfC9n6y-rUqJuhdcpZQ",
      "threadId": "F4Lo07Ls2uXZHq9pHEH73"
    },
    {
      "id": "dnlU7zTBBXEs0q1aA2mMT",
      "seq": 58,
      "at": "2026-07-08T23:01:19.725Z",
      "type": "edge_created",
      "payload": {
        "edge": {
          "id": "m-rXCK6wbyCE5cYMgAhy8",
          "type": "inconsistent_with",
          "from": "DKKqs5O4yDwEaaS5aNSnY",
          "to": "JUgKHcme2oRbzU-6FZZe2",
          "createdAt": "2026-07-08T23:01:19.725Z"
        }
      },
      "edgeId": "m-rXCK6wbyCE5cYMgAhy8",
      "threadId": "F4Lo07Ls2uXZHq9pHEH73"
    },
    {
      "id": "6eAdJ_HA7ut0Q-gqFzNhp",
      "seq": 59,
      "at": "2026-07-08T23:02:06.725Z",
      "type": "edge_created",
      "payload": {
        "edge": {
          "id": "Ou-dWe6TX-bH2n_P48l22",
          "type": "consistent_with",
          "from": "lOcH6_eyof6KJOU2Wl6xv",
          "to": "J59lyA1PwKWOgP0p9AQc0",
          "createdAt": "2026-07-08T23:02:06.725Z"
        }
      },
      "edgeId": "Ou-dWe6TX-bH2n_P48l22",
      "threadId": "F4Lo07Ls2uXZHq9pHEH73"
    },
    {
      "id": "D_JYZcghTVQZB21tBt86z",
      "seq": 60,
      "at": "2026-07-08T23:02:53.725Z",
      "type": "edge_created",
      "payload": {
        "edge": {
          "id": "UpEKFhn1RpcT4eDcaSKQe",
          "type": "consistent_with",
          "from": "lOcH6_eyof6KJOU2Wl6xv",
          "to": "1kMNXyC-mMe4Z_tyEK9hz",
          "createdAt": "2026-07-08T23:02:53.725Z"
        }
      },
      "edgeId": "UpEKFhn1RpcT4eDcaSKQe",
      "threadId": "F4Lo07Ls2uXZHq9pHEH73"
    },
    {
      "id": "JrN9krClhW_6BCG4L_k1_",
      "seq": 61,
      "at": "2026-07-08T23:03:40.725Z",
      "type": "edge_created",
      "payload": {
        "edge": {
          "id": "fivKqBST17wgrkATGIR1u",
          "type": "consistent_with",
          "from": "lOcH6_eyof6KJOU2Wl6xv",
          "to": "JUgKHcme2oRbzU-6FZZe2",
          "createdAt": "2026-07-08T23:03:40.725Z"
        }
      },
      "edgeId": "fivKqBST17wgrkATGIR1u",
      "threadId": "F4Lo07Ls2uXZHq9pHEH73"
    },
    {
      "id": "fFJaWIjIbS5z0pppj-Cho",
      "seq": 62,
      "at": "2026-07-08T23:04:27.725Z",
      "type": "edge_created",
      "payload": {
        "edge": {
          "id": "cbwJDcRqsTSQ3V_sEYuBB",
          "type": "consistent_with",
          "from": "cNK0zJjA5FEzGP5fehN0b",
          "to": "JUgKHcme2oRbzU-6FZZe2",
          "createdAt": "2026-07-08T23:04:27.725Z"
        }
      },
      "edgeId": "cbwJDcRqsTSQ3V_sEYuBB",
      "threadId": "F4Lo07Ls2uXZHq9pHEH73"
    },
    {
      "id": "n9kRXUk6NTJXa8JDtOfok",
      "seq": 63,
      "at": "2026-07-08T23:05:14.725Z",
      "type": "edge_created",
      "payload": {
        "edge": {
          "id": "ZuBzrlqvkCL9ulheLBgtf",
          "type": "inconsistent_with",
          "from": "cNK0zJjA5FEzGP5fehN0b",
          "to": "J59lyA1PwKWOgP0p9AQc0",
          "createdAt": "2026-07-08T23:05:14.725Z"
        }
      },
      "edgeId": "ZuBzrlqvkCL9ulheLBgtf",
      "threadId": "F4Lo07Ls2uXZHq9pHEH73"
    },
    {
      "id": "KU6CPGnRMnVkuUI5hy9OO",
      "seq": 64,
      "at": "2026-07-08T23:06:01.725Z",
      "type": "edge_created",
      "payload": {
        "edge": {
          "id": "GxdnPdoYuRvG8j251vwwn",
          "type": "consistent_with",
          "from": "jL_3WrN01R7_5DcN2VPGH",
          "to": "JUgKHcme2oRbzU-6FZZe2",
          "createdAt": "2026-07-08T23:06:01.725Z"
        }
      },
      "edgeId": "GxdnPdoYuRvG8j251vwwn",
      "threadId": "F4Lo07Ls2uXZHq9pHEH73"
    },
    {
      "id": "5zlxR39uqKznO3e77ayTK",
      "seq": 65,
      "at": "2026-07-08T23:06:48.725Z",
      "type": "edge_created",
      "payload": {
        "edge": {
          "id": "T_jy3-adCAiYj9pXU-dEl",
          "type": "consistent_with",
          "from": "jL_3WrN01R7_5DcN2VPGH",
          "to": "1kMNXyC-mMe4Z_tyEK9hz",
          "createdAt": "2026-07-08T23:06:48.725Z"
        }
      },
      "edgeId": "T_jy3-adCAiYj9pXU-dEl",
      "threadId": "F4Lo07Ls2uXZHq9pHEH73"
    },
    {
      "id": "O_IKMg7s_Fw57cxixypMo",
      "seq": 66,
      "at": "2026-07-08T23:07:35.725Z",
      "type": "edge_created",
      "payload": {
        "edge": {
          "id": "rkN3e62KJAXhB80GX6BUT",
          "type": "consistent_with",
          "from": "BEoS8RZFx2E1I2qk0d5f2",
          "to": "1kMNXyC-mMe4Z_tyEK9hz",
          "createdAt": "2026-07-08T23:07:35.725Z"
        }
      },
      "edgeId": "rkN3e62KJAXhB80GX6BUT",
      "threadId": "F4Lo07Ls2uXZHq9pHEH73"
    },
    {
      "id": "Cl3mYzTnXWLoqKx8WLRfI",
      "seq": 67,
      "at": "2026-07-08T23:08:22.725Z",
      "type": "edge_created",
      "payload": {
        "edge": {
          "id": "VcCg3ZhAmCroaUh1Hm8G3",
          "type": "consistent_with",
          "from": "6EmdJnCl1l0_vF4SP40IG",
          "to": "1kMNXyC-mMe4Z_tyEK9hz",
          "createdAt": "2026-07-08T23:08:22.725Z"
        }
      },
      "edgeId": "VcCg3ZhAmCroaUh1Hm8G3",
      "threadId": "F4Lo07Ls2uXZHq9pHEH73"
    },
    {
      "id": "kZNq1mikr_8xItO923tLh",
      "seq": 68,
      "at": "2026-07-08T23:09:09.725Z",
      "type": "edge_created",
      "payload": {
        "edge": {
          "id": "YC74rl1Gn7wD0mtCZoYLt",
          "type": "inconsistent_with",
          "from": "6EmdJnCl1l0_vF4SP40IG",
          "to": "J59lyA1PwKWOgP0p9AQc0",
          "createdAt": "2026-07-08T23:09:09.725Z"
        }
      },
      "edgeId": "YC74rl1Gn7wD0mtCZoYLt",
      "threadId": "F4Lo07Ls2uXZHq9pHEH73"
    },
    {
      "id": "LBmfuURGPeQJfsuNm5Gcw",
      "seq": 69,
      "at": "2026-07-08T23:09:56.725Z",
      "type": "edge_created",
      "payload": {
        "edge": {
          "id": "dHybtbANCeS9IycYb8jtC",
          "type": "consistent_with",
          "from": "iSShZhcofDGMCk7Fm2LQ3",
          "to": "JUgKHcme2oRbzU-6FZZe2",
          "createdAt": "2026-07-08T23:09:56.725Z"
        }
      },
      "edgeId": "dHybtbANCeS9IycYb8jtC",
      "threadId": "F4Lo07Ls2uXZHq9pHEH73"
    },
    {
      "id": "I1Hbk_pzvlje4U-_XnOat",
      "seq": 70,
      "at": "2026-07-08T23:10:43.725Z",
      "type": "judgement_affirmed",
      "payload": {
        "fields": {
          "likelihood": "realistic_possibility",
          "confidence": "low"
        }
      },
      "nodeId": "1kMNXyC-mMe4Z_tyEK9hz",
      "threadId": "F4Lo07Ls2uXZHq9pHEH73"
    },
    {
      "id": "_amY9nTTDVRFlY20VMrhS",
      "seq": 71,
      "at": "2026-07-08T23:11:30.725Z",
      "type": "judgement_affirmed",
      "payload": {
        "fields": {
          "likelihood": "unlikely",
          "confidence": "low"
        }
      },
      "nodeId": "JUgKHcme2oRbzU-6FZZe2",
      "threadId": "F4Lo07Ls2uXZHq9pHEH73"
    },
    {
      "id": "omUyhAhU13Jd25eNq-x0I",
      "seq": 72,
      "at": "2026-07-08T23:12:17.725Z",
      "type": "thread_created",
      "payload": {
        "rootQuestionId": "edWnPwcXCSAfJnQc_cb6G",
        "parentThreadId": "F4Lo07Ls2uXZHq9pHEH73"
      },
      "nodeId": "edWnPwcXCSAfJnQc_cb6G",
      "threadId": "edWnPwcXCSAfJnQc_cb6G"
    },
    {
      "id": "KPIlmI5_n8lXERiCCgAtD",
      "seq": 73,
      "at": "2026-07-08T23:13:04.725Z",
      "type": "node_created",
      "payload": {
        "node": {
          "id": "edWnPwcXCSAfJnQc_cb6G",
          "text": "Was the loader custom-built?",
          "x": 60,
          "y": 60,
          "createdAt": "2026-07-08T23:13:04.725Z",
          "stale": {
            "kind": "fresh"
          },
          "type": "question",
          "threadId": "edWnPwcXCSAfJnQc_cb6G",
          "status": "open",
          "mutuallyExclusive": false,
          "parentThreadId": "F4Lo07Ls2uXZHq9pHEH73"
        },
        "captureMs": 8000
      },
      "nodeId": "edWnPwcXCSAfJnQc_cb6G",
      "threadId": "edWnPwcXCSAfJnQc_cb6G"
    },
    {
      "id": "pRI9IryTQHnr3NxqCImte",
      "seq": 74,
      "at": "2026-07-08T23:13:51.725Z",
      "type": "node_created",
      "payload": {
        "node": {
          "id": "O1EZzp-7ROLVuI10h51tp",
          "text": "The loader was custom-built for this intrusion",
          "x": 160,
          "y": 240,
          "createdAt": "2026-07-08T23:13:51.725Z",
          "stale": {
            "kind": "fresh"
          },
          "type": "claim",
          "threadId": "edWnPwcXCSAfJnQc_cb6G",
          "status": "open"
        },
        "captureMs": 8000
      },
      "nodeId": "O1EZzp-7ROLVuI10h51tp",
      "threadId": "edWnPwcXCSAfJnQc_cb6G"
    },
    {
      "id": "DoO8UZ6Xyk7gZipVEC7VO",
      "seq": 75,
      "at": "2026-07-08T23:14:38.725Z",
      "type": "judgement_declared",
      "payload": {
        "field": "likelihood",
        "before": null,
        "after": "likely"
      },
      "nodeId": "O1EZzp-7ROLVuI10h51tp",
      "threadId": "edWnPwcXCSAfJnQc_cb6G"
    },
    {
      "id": "QuUMyHnnE03PdvY9EqqB3",
      "seq": 76,
      "at": "2026-07-08T23:15:25.725Z",
      "type": "judgement_declared",
      "payload": {
        "field": "confidence",
        "before": null,
        "after": "moderate"
      },
      "nodeId": "O1EZzp-7ROLVuI10h51tp",
      "threadId": "edWnPwcXCSAfJnQc_cb6G"
    },
    {
      "id": "m69R2klgOv7_m9hZH3r9H",
      "seq": 77,
      "at": "2026-07-08T23:16:12.725Z",
      "type": "node_created",
      "payload": {
        "node": {
          "id": "kFKpiOCof28uB0RWmoYL3",
          "text": "The loader was assembled from a leaked builder",
          "x": 460,
          "y": 240,
          "createdAt": "2026-07-08T23:16:12.725Z",
          "stale": {
            "kind": "fresh"
          },
          "type": "claim",
          "threadId": "edWnPwcXCSAfJnQc_cb6G",
          "status": "open"
        },
        "captureMs": 3000
      },
      "nodeId": "kFKpiOCof28uB0RWmoYL3",
      "threadId": "edWnPwcXCSAfJnQc_cb6G"
    },
    {
      "id": "-jsKT_EAUZU_2FW_OWjMK",
      "seq": 78,
      "at": "2026-07-08T23:16:59.725Z",
      "type": "judgement_declared",
      "payload": {
        "field": "likelihood",
        "before": null,
        "after": "unlikely"
      },
      "nodeId": "kFKpiOCof28uB0RWmoYL3",
      "threadId": "edWnPwcXCSAfJnQc_cb6G"
    },
    {
      "id": "b9IPx-H0aVUQsRZsb5Ih7",
      "seq": 79,
      "at": "2026-07-08T23:17:46.725Z",
      "type": "judgement_declared",
      "payload": {
        "field": "confidence",
        "before": null,
        "after": "low"
      },
      "nodeId": "kFKpiOCof28uB0RWmoYL3",
      "threadId": "edWnPwcXCSAfJnQc_cb6G"
    },
    {
      "id": "Qh5MqUC1i0qKN8FtlOlnY",
      "seq": 80,
      "at": "2026-07-08T23:18:33.725Z",
      "type": "edge_created",
      "payload": {
        "edge": {
          "id": "WtlGViGp79DcWLhbvfZGo",
          "type": "answers",
          "from": "O1EZzp-7ROLVuI10h51tp",
          "to": "edWnPwcXCSAfJnQc_cb6G",
          "createdAt": "2026-07-08T23:18:33.725Z"
        }
      },
      "edgeId": "WtlGViGp79DcWLhbvfZGo",
      "threadId": "edWnPwcXCSAfJnQc_cb6G"
    },
    {
      "id": "EuwHxVuQ7nnOl1zFc4Y2e",
      "seq": 81,
      "at": "2026-07-08T23:19:20.725Z",
      "type": "edge_created",
      "payload": {
        "edge": {
          "id": "8xukSGrlZf1pW_lCbDlWO",
          "type": "answers",
          "from": "kFKpiOCof28uB0RWmoYL3",
          "to": "edWnPwcXCSAfJnQc_cb6G",
          "createdAt": "2026-07-08T23:19:20.725Z"
        }
      },
      "edgeId": "8xukSGrlZf1pW_lCbDlWO",
      "threadId": "edWnPwcXCSAfJnQc_cb6G"
    },
    {
      "id": "yARSipOhqliM4l_ZJFwMV",
      "seq": 82,
      "at": "2026-07-08T23:20:07.725Z",
      "type": "node_created",
      "payload": {
        "node": {
          "id": "X6Ws-hHkbBG7POvuE4mEL",
          "text": "No builder artifacts for this loader found in the wild",
          "x": 300,
          "y": 480,
          "createdAt": "2026-07-08T23:20:07.725Z",
          "stale": {
            "kind": "fresh"
          },
          "type": "evidence",
          "threadId": "edWnPwcXCSAfJnQc_cb6G"
        },
        "captureMs": 4000
      },
      "nodeId": "X6Ws-hHkbBG7POvuE4mEL",
      "threadId": "edWnPwcXCSAfJnQc_cb6G"
    },
    {
      "id": "d3RQwQ0Pd1n8BcGjbiUXU",
      "seq": 83,
      "at": "2026-07-08T23:20:54.725Z",
      "type": "judgement_declared",
      "payload": {
        "field": "sourceReliability",
        "before": null,
        "after": "C"
      },
      "nodeId": "X6Ws-hHkbBG7POvuE4mEL",
      "threadId": "edWnPwcXCSAfJnQc_cb6G"
    },
    {
      "id": "glmJ1pbXwa32BBR0pVUnd",
      "seq": 84,
      "at": "2026-07-08T23:21:41.725Z",
      "type": "judgement_declared",
      "payload": {
        "field": "infoCredibility",
        "before": null,
        "after": 2
      },
      "nodeId": "X6Ws-hHkbBG7POvuE4mEL",
      "threadId": "edWnPwcXCSAfJnQc_cb6G"
    },
    {
      "id": "dDfAz-aGz_PTBnPNVbjUD",
      "seq": 85,
      "at": "2026-07-08T23:22:28.725Z",
      "type": "edge_created",
      "payload": {
        "edge": {
          "id": "BJWp1REnhV8Actu4xwkDi",
          "type": "consistent_with",
          "from": "X6Ws-hHkbBG7POvuE4mEL",
          "to": "O1EZzp-7ROLVuI10h51tp",
          "createdAt": "2026-07-08T23:22:28.725Z"
        }
      },
      "edgeId": "BJWp1REnhV8Actu4xwkDi",
      "threadId": "edWnPwcXCSAfJnQc_cb6G"
    },
    {
      "id": "0yhUKu9rW_lfKzrAjn1cO",
      "seq": 86,
      "at": "2026-07-08T23:23:15.725Z",
      "type": "edge_created",
      "payload": {
        "edge": {
          "id": "Cw5bHlRARlf7TK-PdVmBm",
          "type": "inconsistent_with",
          "from": "X6Ws-hHkbBG7POvuE4mEL",
          "to": "kFKpiOCof28uB0RWmoYL3",
          "createdAt": "2026-07-08T23:23:15.725Z"
        }
      },
      "edgeId": "Cw5bHlRARlf7TK-PdVmBm",
      "threadId": "edWnPwcXCSAfJnQc_cb6G"
    },
    {
      "id": "nSdV6q7RmDQ_1_mvXPh0z",
      "seq": 87,
      "at": "2026-07-08T23:24:02.725Z",
      "type": "judgement_affirmed",
      "payload": {
        "fields": {
          "likelihood": "unlikely",
          "confidence": "low"
        }
      },
      "nodeId": "kFKpiOCof28uB0RWmoYL3",
      "threadId": "edWnPwcXCSAfJnQc_cb6G"
    },
    {
      "id": "q5qj19jSFEPYzIePCLssV",
      "seq": 88,
      "at": "2026-07-08T23:24:49.725Z",
      "type": "claim_status_changed",
      "payload": {
        "before": "open",
        "after": "adopted",
        "ceremony": {
          "at": "2026-07-10T22:25:17.711Z",
          "candidate": {
            "id": "O1EZzp-7ROLVuI10h51tp",
            "text": "The loader was custom-built for this intrusion",
            "iCount": 0
          },
          "rivals": [
            {
              "id": "kFKpiOCof28uB0RWmoYL3",
              "text": "The loader was assembled from a leaked builder",
              "status": "open",
              "iCount": 1,
              "disconfirmationAttempted": true
            }
          ],
          "linchpins": []
        }
      },
      "nodeId": "O1EZzp-7ROLVuI10h51tp",
      "threadId": "edWnPwcXCSAfJnQc_cb6G"
    },
    {
      "id": "RvJkpx3DYO6QyUcjgFayz",
      "seq": 89,
      "at": "2026-07-08T23:25:36.725Z",
      "type": "question_status_changed",
      "payload": {
        "before": "open",
        "after": "answered",
        "byClaim": "O1EZzp-7ROLVuI10h51tp"
      },
      "nodeId": "edWnPwcXCSAfJnQc_cb6G",
      "threadId": "edWnPwcXCSAfJnQc_cb6G"
    },
    {
      "id": "AgAwP-VWXqqv0eMQh790-",
      "seq": 90,
      "at": "2026-07-08T23:26:23.725Z",
      "type": "node_promoted",
      "payload": {
        "sourceClaimId": "O1EZzp-7ROLVuI10h51tp",
        "asType": "evidence",
        "node": {
          "id": "FyQcj2ky8tpl1dautOBRY",
          "text": "The loader was custom-built for this intrusion",
          "threadId": "F4Lo07Ls2uXZHq9pHEH73",
          "x": 90,
          "y": 980,
          "createdAt": "2026-07-08T23:26:23.725Z",
          "derivedFrom": "O1EZzp-7ROLVuI10h51tp",
          "stale": {
            "kind": "fresh"
          },
          "type": "evidence"
        }
      },
      "nodeId": "FyQcj2ky8tpl1dautOBRY",
      "threadId": "F4Lo07Ls2uXZHq9pHEH73"
    },
    {
      "id": "IJ8YpVDHYMnjvcApy7Lzz",
      "seq": 91,
      "at": "2026-07-08T23:27:10.725Z",
      "type": "judgement_declared",
      "payload": {
        "field": "sourceReliability",
        "before": null,
        "after": "B"
      },
      "nodeId": "FyQcj2ky8tpl1dautOBRY",
      "threadId": "F4Lo07Ls2uXZHq9pHEH73"
    },
    {
      "id": "gg0O5m7uVbO-84nNUQ97c",
      "seq": 92,
      "at": "2026-07-08T23:27:57.725Z",
      "type": "judgement_declared",
      "payload": {
        "field": "infoCredibility",
        "before": null,
        "after": 3
      },
      "nodeId": "FyQcj2ky8tpl1dautOBRY",
      "threadId": "F4Lo07Ls2uXZHq9pHEH73"
    },
    {
      "id": "99hse1BCz0BVuaXabHLGT",
      "seq": 93,
      "at": "2026-07-08T23:28:44.725Z",
      "type": "edge_created",
      "payload": {
        "edge": {
          "id": "OBji7M3OiGq5G7bZf4WuT",
          "type": "consistent_with",
          "from": "FyQcj2ky8tpl1dautOBRY",
          "to": "J59lyA1PwKWOgP0p9AQc0",
          "createdAt": "2026-07-08T23:28:44.725Z"
        }
      },
      "edgeId": "OBji7M3OiGq5G7bZf4WuT",
      "threadId": "F4Lo07Ls2uXZHq9pHEH73"
    },
    {
      "id": "YFXOY9c3dpG8-YdFEcAs_",
      "seq": 94,
      "at": "2026-07-08T23:29:31.725Z",
      "type": "judgement_affirmed",
      "payload": {
        "fields": {
          "likelihood": "likely",
          "confidence": "moderate"
        }
      },
      "nodeId": "J59lyA1PwKWOgP0p9AQc0",
      "threadId": "F4Lo07Ls2uXZHq9pHEH73"
    },
    {
      "id": "v0NJStcNp-pb-lt6t_05y",
      "seq": 95,
      "at": "2026-07-08T23:30:18.725Z",
      "type": "thread_created",
      "payload": {
        "rootQuestionId": "OaxvsgY48sfxSCLBHLvwf",
        "parentThreadId": "F4Lo07Ls2uXZHq9pHEH73"
      },
      "nodeId": "OaxvsgY48sfxSCLBHLvwf",
      "threadId": "OaxvsgY48sfxSCLBHLvwf"
    },
    {
      "id": "nLIpJUXfpX-bicrC1_YYC",
      "seq": 96,
      "at": "2026-07-08T23:31:05.725Z",
      "type": "node_created",
      "payload": {
        "node": {
          "id": "OaxvsgY48sfxSCLBHLvwf",
          "text": "Who had physical access to the build server?",
          "x": 1040,
          "y": 60,
          "createdAt": "2026-07-08T23:31:05.725Z",
          "stale": {
            "kind": "fresh"
          },
          "type": "question",
          "threadId": "OaxvsgY48sfxSCLBHLvwf",
          "status": "open",
          "mutuallyExclusive": false,
          "parentThreadId": "F4Lo07Ls2uXZHq9pHEH73"
        },
        "captureMs": 8000
      },
      "nodeId": "OaxvsgY48sfxSCLBHLvwf",
      "threadId": "OaxvsgY48sfxSCLBHLvwf"
    },
    {
      "id": "RmRZNBqK_G6NIiqxlnwQR",
      "seq": 97,
      "at": "2026-07-08T23:31:52.725Z",
      "type": "judgement_declared",
      "payload": {
        "field": "priority",
        "before": null,
        "after": "high"
      },
      "nodeId": "OaxvsgY48sfxSCLBHLvwf",
      "threadId": "OaxvsgY48sfxSCLBHLvwf"
    },
    {
      "id": "dhnoW05hqzY7hWgM8GIiB",
      "seq": 98,
      "at": "2026-07-08T23:32:39.725Z",
      "type": "thread_created",
      "payload": {
        "rootIncidentId": "o0V81_wVv3JjXJfyj34re",
        "workflow": "diamond"
      },
      "nodeId": "o0V81_wVv3JjXJfyj34re",
      "threadId": "o0V81_wVv3JjXJfyj34re"
    },
    {
      "id": "-o5enh-NpWcNUkgg0rjLg",
      "seq": 99,
      "at": "2026-07-08T23:33:26.725Z",
      "type": "node_created",
      "payload": {
        "node": {
          "id": "o0V81_wVv3JjXJfyj34re",
          "text": "Intrusion at ACME — June 2026",
          "x": 420,
          "y": 40,
          "createdAt": "2026-07-08T23:33:26.725Z",
          "stale": {
            "kind": "fresh"
          },
          "type": "incident",
          "threadId": "o0V81_wVv3JjXJfyj34re",
          "status": "open"
        }
      },
      "nodeId": "o0V81_wVv3JjXJfyj34re",
      "threadId": "o0V81_wVv3JjXJfyj34re"
    },
    {
      "id": "RQUHOuQaI6a2jouqk2sHE",
      "seq": 100,
      "at": "2026-07-08T23:34:13.725Z",
      "type": "node_created",
      "payload": {
        "node": {
          "id": "zXQvwOk0uFRmHDPKQcJQu",
          "text": "Finance-themed phishing lure delivered to 41 staff",
          "x": 80,
          "y": 240,
          "createdAt": "2026-07-08T23:34:13.725Z",
          "stale": {
            "kind": "fresh"
          },
          "type": "diamond_event",
          "threadId": "o0V81_wVv3JjXJfyj34re"
        },
        "captureMs": 7000
      },
      "nodeId": "zXQvwOk0uFRmHDPKQcJQu",
      "threadId": "o0V81_wVv3JjXJfyj34re"
    },
    {
      "id": "EPng_RRsLgBOc5MLg1KJa",
      "seq": 101,
      "at": "2026-07-08T23:35:00.725Z",
      "type": "judgement_declared",
      "payload": {
        "field": "phase",
        "before": null,
        "after": "delivery"
      },
      "nodeId": "zXQvwOk0uFRmHDPKQcJQu",
      "threadId": "o0V81_wVv3JjXJfyj34re"
    },
    {
      "id": "t28UIm7hyPVNC7jpRz8AH",
      "seq": 102,
      "at": "2026-07-08T23:35:47.725Z",
      "type": "judgement_declared",
      "payload": {
        "field": "result",
        "before": null,
        "after": "success"
      },
      "nodeId": "zXQvwOk0uFRmHDPKQcJQu",
      "threadId": "o0V81_wVv3JjXJfyj34re"
    },
    {
      "id": "PsDnDX-KnkEuYfLnN6z2a",
      "seq": 103,
      "at": "2026-07-08T23:36:34.725Z",
      "type": "judgement_declared",
      "payload": {
        "field": "direction",
        "before": null,
        "after": "infrastructure_to_victim"
      },
      "nodeId": "zXQvwOk0uFRmHDPKQcJQu",
      "threadId": "o0V81_wVv3JjXJfyj34re"
    },
    {
      "id": "kFdVOIHPAb-oTIDV2SBNn",
      "seq": 104,
      "at": "2026-07-08T23:37:21.725Z",
      "type": "judgement_declared",
      "payload": {
        "field": "occurredAt",
        "before": null,
        "after": "2026-06-09"
      },
      "nodeId": "zXQvwOk0uFRmHDPKQcJQu",
      "threadId": "o0V81_wVv3JjXJfyj34re"
    },
    {
      "id": "FsaCi2XzMuaNz_40laGCC",
      "seq": 105,
      "at": "2026-07-08T23:38:08.725Z",
      "type": "node_created",
      "payload": {
        "node": {
          "id": "vFw5lYGhOS0vOJsWAG4jZ",
          "text": "KESTREL loader executed on FIN-WS-041",
          "x": 380,
          "y": 240,
          "createdAt": "2026-07-08T23:38:08.725Z",
          "stale": {
            "kind": "fresh"
          },
          "type": "diamond_event",
          "threadId": "o0V81_wVv3JjXJfyj34re"
        },
        "captureMs": 9000
      },
      "nodeId": "vFw5lYGhOS0vOJsWAG4jZ",
      "threadId": "o0V81_wVv3JjXJfyj34re"
    },
    {
      "id": "bpGWTyvJK6exveiiwtGI7",
      "seq": 106,
      "at": "2026-07-08T23:38:55.725Z",
      "type": "judgement_declared",
      "payload": {
        "field": "phase",
        "before": null,
        "after": "exploitation"
      },
      "nodeId": "vFw5lYGhOS0vOJsWAG4jZ",
      "threadId": "o0V81_wVv3JjXJfyj34re"
    },
    {
      "id": "7hD8WSTEVr2GsE7AlBOBY",
      "seq": 107,
      "at": "2026-07-08T23:39:42.725Z",
      "type": "judgement_declared",
      "payload": {
        "field": "result",
        "before": null,
        "after": "success"
      },
      "nodeId": "vFw5lYGhOS0vOJsWAG4jZ",
      "threadId": "o0V81_wVv3JjXJfyj34re"
    },
    {
      "id": "dF5pBTskEIWZjmx_1I2ZS",
      "seq": 108,
      "at": "2026-07-08T23:40:29.725Z",
      "type": "judgement_declared",
      "payload": {
        "field": "direction",
        "before": null,
        "after": "infrastructure_to_victim"
      },
      "nodeId": "vFw5lYGhOS0vOJsWAG4jZ",
      "threadId": "o0V81_wVv3JjXJfyj34re"
    },
    {
      "id": "hJYnvDgL58zHwF3mLz-PW",
      "seq": 109,
      "at": "2026-07-08T23:41:16.725Z",
      "type": "judgement_declared",
      "payload": {
        "field": "occurredAt",
        "before": null,
        "after": "2026-06-09"
      },
      "nodeId": "vFw5lYGhOS0vOJsWAG4jZ",
      "threadId": "o0V81_wVv3JjXJfyj34re"
    },
    {
      "id": "SwTL7keYvLxWCN-EoXmr3",
      "seq": 110,
      "at": "2026-07-08T23:42:03.725Z",
      "type": "node_created",
      "payload": {
        "node": {
          "id": "2QGmwgq7dNoofVc9uR5ze",
          "text": "Beaconing to bulletproof host 45.155.87.12",
          "x": 680,
          "y": 240,
          "createdAt": "2026-07-08T23:42:03.725Z",
          "stale": {
            "kind": "fresh"
          },
          "type": "diamond_event",
          "threadId": "o0V81_wVv3JjXJfyj34re"
        },
        "captureMs": 4000
      },
      "nodeId": "2QGmwgq7dNoofVc9uR5ze",
      "threadId": "o0V81_wVv3JjXJfyj34re"
    },
    {
      "id": "FGQQIvzdj-Wb73pyl9qr9",
      "seq": 111,
      "at": "2026-07-08T23:42:50.725Z",
      "type": "judgement_declared",
      "payload": {
        "field": "phase",
        "before": null,
        "after": "command_and_control"
      },
      "nodeId": "2QGmwgq7dNoofVc9uR5ze",
      "threadId": "o0V81_wVv3JjXJfyj34re"
    },
    {
      "id": "2HF-9HH_DJA3P3Al5XoyY",
      "seq": 112,
      "at": "2026-07-08T23:43:37.725Z",
      "type": "judgement_declared",
      "payload": {
        "field": "result",
        "before": null,
        "after": "success"
      },
      "nodeId": "2QGmwgq7dNoofVc9uR5ze",
      "threadId": "o0V81_wVv3JjXJfyj34re"
    },
    {
      "id": "WCC6Yo1g8UKkA9hZYZvsZ",
      "seq": 113,
      "at": "2026-07-08T23:44:24.725Z",
      "type": "judgement_declared",
      "payload": {
        "field": "direction",
        "before": null,
        "after": "bidirectional"
      },
      "nodeId": "2QGmwgq7dNoofVc9uR5ze",
      "threadId": "o0V81_wVv3JjXJfyj34re"
    },
    {
      "id": "jdfqZwIilPY1LP3fDlVbB",
      "seq": 114,
      "at": "2026-07-08T23:45:11.725Z",
      "type": "judgement_declared",
      "payload": {
        "field": "occurredAt",
        "before": null,
        "after": "2026-06-10"
      },
      "nodeId": "2QGmwgq7dNoofVc9uR5ze",
      "threadId": "o0V81_wVv3JjXJfyj34re"
    },
    {
      "id": "29Dz5d0wsMyy9Zam65nJ8",
      "seq": 115,
      "at": "2026-07-08T23:45:58.725Z",
      "type": "node_created",
      "payload": {
        "node": {
          "id": "MSVV96HWDyZKFGz_pQyu5",
          "text": "Staged archive exfiltrated over HTTPS",
          "x": 980,
          "y": 240,
          "createdAt": "2026-07-08T23:45:58.725Z",
          "stale": {
            "kind": "fresh"
          },
          "type": "diamond_event",
          "threadId": "o0V81_wVv3JjXJfyj34re"
        },
        "captureMs": 6000
      },
      "nodeId": "MSVV96HWDyZKFGz_pQyu5",
      "threadId": "o0V81_wVv3JjXJfyj34re"
    },
    {
      "id": "0l0DQ0RmAo5B98K76Ijf-",
      "seq": 116,
      "at": "2026-07-08T23:46:45.725Z",
      "type": "judgement_declared",
      "payload": {
        "field": "phase",
        "before": null,
        "after": "actions_on_objectives"
      },
      "nodeId": "MSVV96HWDyZKFGz_pQyu5",
      "threadId": "o0V81_wVv3JjXJfyj34re"
    },
    {
      "id": "VVAhQUDG2uneudurTYPF3",
      "seq": 117,
      "at": "2026-07-08T23:47:32.725Z",
      "type": "judgement_declared",
      "payload": {
        "field": "result",
        "before": null,
        "after": "success"
      },
      "nodeId": "MSVV96HWDyZKFGz_pQyu5",
      "threadId": "o0V81_wVv3JjXJfyj34re"
    },
    {
      "id": "5iKoUe2U5P8gZHEd1lWWf",
      "seq": 118,
      "at": "2026-07-08T23:48:19.725Z",
      "type": "judgement_declared",
      "payload": {
        "field": "direction",
        "before": null,
        "after": "victim_to_infrastructure"
      },
      "nodeId": "MSVV96HWDyZKFGz_pQyu5",
      "threadId": "o0V81_wVv3JjXJfyj34re"
    },
    {
      "id": "ZUp61LnGqmO67JO89mYHN",
      "seq": 119,
      "at": "2026-07-08T23:49:06.725Z",
      "type": "judgement_declared",
      "payload": {
        "field": "occurredAt",
        "before": null,
        "after": "2026-06-11"
      },
      "nodeId": "MSVV96HWDyZKFGz_pQyu5",
      "threadId": "o0V81_wVv3JjXJfyj34re"
    },
    {
      "id": "yQxvEfzO90AzwvgnUSVWM",
      "seq": 120,
      "at": "2026-07-08T23:49:53.725Z",
      "type": "node_created",
      "payload": {
        "node": {
          "id": "YD-1w7WZ5XduZIk8lYmtS",
          "text": "RDP login from dormant service account",
          "x": 1280,
          "y": 240,
          "createdAt": "2026-07-08T23:49:53.725Z",
          "stale": {
            "kind": "fresh"
          },
          "type": "diamond_event",
          "threadId": "o0V81_wVv3JjXJfyj34re"
        },
        "captureMs": 8000
      },
      "nodeId": "YD-1w7WZ5XduZIk8lYmtS",
      "threadId": "o0V81_wVv3JjXJfyj34re"
    },
    {
      "id": "oGAw0ypZbYSXCXkY4Miq2",
      "seq": 121,
      "at": "2026-07-08T23:50:40.725Z",
      "type": "node_created",
      "payload": {
        "node": {
          "id": "_xh2PpXsbBFz5zEu6_rPP",
          "text": "Unattributed — tracked as UNC-ACME",
          "x": 680,
          "y": 60,
          "createdAt": "2026-07-08T23:50:40.725Z",
          "stale": {
            "kind": "fresh"
          },
          "type": "adversary",
          "threadId": "o0V81_wVv3JjXJfyj34re"
        },
        "captureMs": 7000
      },
      "nodeId": "_xh2PpXsbBFz5zEu6_rPP",
      "threadId": "o0V81_wVv3JjXJfyj34re"
    },
    {
      "id": "fOKRnRbX26Rq_uCfVRawh",
      "seq": 122,
      "at": "2026-07-08T23:51:27.725Z",
      "type": "judgement_declared",
      "payload": {
        "field": "confidence",
        "before": null,
        "after": "low"
      },
      "nodeId": "_xh2PpXsbBFz5zEu6_rPP",
      "threadId": "o0V81_wVv3JjXJfyj34re"
    },
    {
      "id": "ahK1SSKIE2fE5cX4yTng-",
      "seq": 123,
      "at": "2026-07-08T23:52:14.725Z",
      "type": "node_created",
      "payload": {
        "node": {
          "id": "JZCFeln-RZWg65zNpA8d6",
          "text": "KESTREL loader (custom build)",
          "x": 300,
          "y": 460,
          "createdAt": "2026-07-08T23:52:14.725Z",
          "stale": {
            "kind": "fresh"
          },
          "type": "capability",
          "threadId": "o0V81_wVv3JjXJfyj34re"
        },
        "captureMs": 9000
      },
      "nodeId": "JZCFeln-RZWg65zNpA8d6",
      "threadId": "o0V81_wVv3JjXJfyj34re"
    },
    {
      "id": "LyZxFwsvS2jU_iaQIE64U",
      "seq": 124,
      "at": "2026-07-08T23:53:01.725Z",
      "type": "judgement_declared",
      "payload": {
        "field": "confidence",
        "before": null,
        "after": "moderate"
      },
      "nodeId": "JZCFeln-RZWg65zNpA8d6",
      "threadId": "o0V81_wVv3JjXJfyj34re"
    },
    {
      "id": "UebzZPX7tRmGGUJgvF_Vo",
      "seq": 125,
      "at": "2026-07-08T23:53:48.725Z",
      "type": "node_created",
      "payload": {
        "node": {
          "id": "XhJVHGWTcSHZYdLOsqPtb",
          "text": "Spear-phish lure, finance theme",
          "x": 60,
          "y": 460,
          "createdAt": "2026-07-08T23:53:48.725Z",
          "stale": {
            "kind": "fresh"
          },
          "type": "capability",
          "threadId": "o0V81_wVv3JjXJfyj34re"
        },
        "captureMs": 6000
      },
      "nodeId": "XhJVHGWTcSHZYdLOsqPtb",
      "threadId": "o0V81_wVv3JjXJfyj34re"
    },
    {
      "id": "YoDuCJx3lq2e2afXrSy5W",
      "seq": 126,
      "at": "2026-07-08T23:54:35.725Z",
      "type": "judgement_declared",
      "payload": {
        "field": "confidence",
        "before": null,
        "after": "moderate"
      },
      "nodeId": "XhJVHGWTcSHZYdLOsqPtb",
      "threadId": "o0V81_wVv3JjXJfyj34re"
    },
    {
      "id": "dwqGEpveJj-xQf_13jfQg",
      "seq": 127,
      "at": "2026-07-08T23:55:22.725Z",
      "type": "node_created",
      "payload": {
        "node": {
          "id": "AvMWn9f1NWbopONzwkucL",
          "text": "Bulletproof host 45.155.87.12 (C2)",
          "x": 760,
          "y": 460,
          "createdAt": "2026-07-08T23:55:22.725Z",
          "stale": {
            "kind": "fresh"
          },
          "type": "infrastructure",
          "threadId": "o0V81_wVv3JjXJfyj34re"
        },
        "captureMs": 6000
      },
      "nodeId": "AvMWn9f1NWbopONzwkucL",
      "threadId": "o0V81_wVv3JjXJfyj34re"
    },
    {
      "id": "fJ-0peutoOpEv7CHKfoCt",
      "seq": 128,
      "at": "2026-07-08T23:56:09.725Z",
      "type": "judgement_declared",
      "payload": {
        "field": "confidence",
        "before": null,
        "after": "high"
      },
      "nodeId": "AvMWn9f1NWbopONzwkucL",
      "threadId": "o0V81_wVv3JjXJfyj34re"
    },
    {
      "id": "Rd01IJQ2Sr8AAThiswQtr",
      "seq": 129,
      "at": "2026-07-08T23:56:56.725Z",
      "type": "node_created",
      "payload": {
        "node": {
          "id": "A93mgK01wEWMR_dKhC2Ya",
          "text": "ACME finance workstation FIN-WS-041",
          "x": 500,
          "y": 620,
          "createdAt": "2026-07-08T23:56:56.725Z",
          "stale": {
            "kind": "fresh"
          },
          "type": "victim",
          "threadId": "o0V81_wVv3JjXJfyj34re"
        },
        "captureMs": 3000
      },
      "nodeId": "A93mgK01wEWMR_dKhC2Ya",
      "threadId": "o0V81_wVv3JjXJfyj34re"
    },
    {
      "id": "-7iymGCVKjozmx2vyJP3M",
      "seq": 130,
      "at": "2026-07-08T23:57:43.725Z",
      "type": "judgement_declared",
      "payload": {
        "field": "confidence",
        "before": null,
        "after": "high"
      },
      "nodeId": "A93mgK01wEWMR_dKhC2Ya",
      "threadId": "o0V81_wVv3JjXJfyj34re"
    },
    {
      "id": "24Ni_Oi2QOsscp1L2fWUX",
      "seq": 131,
      "at": "2026-07-08T23:58:30.725Z",
      "type": "edge_created",
      "payload": {
        "edge": {
          "id": "k1FcjCzksqI1xqAKxqnjk",
          "type": "characterizes",
          "from": "XhJVHGWTcSHZYdLOsqPtb",
          "to": "zXQvwOk0uFRmHDPKQcJQu",
          "createdAt": "2026-07-08T23:58:30.725Z"
        }
      },
      "edgeId": "k1FcjCzksqI1xqAKxqnjk",
      "threadId": "o0V81_wVv3JjXJfyj34re"
    },
    {
      "id": "e7kEyZg4lqudBPafDYUpr",
      "seq": 132,
      "at": "2026-07-08T23:59:17.725Z",
      "type": "edge_created",
      "payload": {
        "edge": {
          "id": "_IS6bhk-mny78LrTNp0g6",
          "type": "characterizes",
          "from": "A93mgK01wEWMR_dKhC2Ya",
          "to": "zXQvwOk0uFRmHDPKQcJQu",
          "createdAt": "2026-07-08T23:59:17.725Z"
        }
      },
      "edgeId": "_IS6bhk-mny78LrTNp0g6",
      "threadId": "o0V81_wVv3JjXJfyj34re"
    },
    {
      "id": "LvC9ZrKWGfk3rVbEmAv1r",
      "seq": 133,
      "at": "2026-07-09T00:00:04.725Z",
      "type": "edge_created",
      "payload": {
        "edge": {
          "id": "-b9yjmwG9mdHR8ahI9OU5",
          "type": "characterizes",
          "from": "JZCFeln-RZWg65zNpA8d6",
          "to": "vFw5lYGhOS0vOJsWAG4jZ",
          "createdAt": "2026-07-09T00:00:04.725Z"
        }
      },
      "edgeId": "-b9yjmwG9mdHR8ahI9OU5",
      "threadId": "o0V81_wVv3JjXJfyj34re"
    },
    {
      "id": "86Cj8Rd2-kIwkwApZ76A9",
      "seq": 134,
      "at": "2026-07-09T00:00:51.725Z",
      "type": "edge_created",
      "payload": {
        "edge": {
          "id": "Gt0vI0-zPMUwShdQQT4vR",
          "type": "characterizes",
          "from": "A93mgK01wEWMR_dKhC2Ya",
          "to": "vFw5lYGhOS0vOJsWAG4jZ",
          "createdAt": "2026-07-09T00:00:51.725Z"
        }
      },
      "edgeId": "Gt0vI0-zPMUwShdQQT4vR",
      "threadId": "o0V81_wVv3JjXJfyj34re"
    },
    {
      "id": "jM7FxmON0eQYt8xF1v9no",
      "seq": 135,
      "at": "2026-07-09T00:01:38.725Z",
      "type": "edge_created",
      "payload": {
        "edge": {
          "id": "2MbK0XhzX2S22oq4PfU3R",
          "type": "characterizes",
          "from": "_xh2PpXsbBFz5zEu6_rPP",
          "to": "2QGmwgq7dNoofVc9uR5ze",
          "createdAt": "2026-07-09T00:01:38.725Z"
        }
      },
      "edgeId": "2MbK0XhzX2S22oq4PfU3R",
      "threadId": "o0V81_wVv3JjXJfyj34re"
    },
    {
      "id": "UZPAvqbXCD38ipYRzCSTP",
      "seq": 136,
      "at": "2026-07-09T00:02:25.725Z",
      "type": "edge_created",
      "payload": {
        "edge": {
          "id": "97huz7CRVDWA8rgnnxqsz",
          "type": "characterizes",
          "from": "AvMWn9f1NWbopONzwkucL",
          "to": "2QGmwgq7dNoofVc9uR5ze",
          "createdAt": "2026-07-09T00:02:25.725Z"
        }
      },
      "edgeId": "97huz7CRVDWA8rgnnxqsz",
      "threadId": "o0V81_wVv3JjXJfyj34re"
    },
    {
      "id": "JlIC-uqTQflL5KDSIFSRd",
      "seq": 137,
      "at": "2026-07-09T00:03:12.725Z",
      "type": "edge_created",
      "payload": {
        "edge": {
          "id": "dOXWXf4kca0A2mtmnFYYC",
          "type": "characterizes",
          "from": "AvMWn9f1NWbopONzwkucL",
          "to": "MSVV96HWDyZKFGz_pQyu5",
          "createdAt": "2026-07-09T00:03:12.725Z"
        }
      },
      "edgeId": "dOXWXf4kca0A2mtmnFYYC",
      "threadId": "o0V81_wVv3JjXJfyj34re"
    },
    {
      "id": "vvNHZycEEMtUIVjpALbVi",
      "seq": 138,
      "at": "2026-07-09T00:03:59.725Z",
      "type": "edge_created",
      "payload": {
        "edge": {
          "id": "smZPjHRqMujBTxIbOdlSN",
          "type": "characterizes",
          "from": "A93mgK01wEWMR_dKhC2Ya",
          "to": "MSVV96HWDyZKFGz_pQyu5",
          "createdAt": "2026-07-09T00:03:59.725Z"
        }
      },
      "edgeId": "smZPjHRqMujBTxIbOdlSN",
      "threadId": "o0V81_wVv3JjXJfyj34re"
    },
    {
      "id": "O-8kydvqdeys_yX6Mi-w7",
      "seq": 139,
      "at": "2026-07-09T00:04:46.725Z",
      "type": "node_created",
      "payload": {
        "node": {
          "id": "TKS4wNrTpCWKTqM8PzbV5",
          "text": "Mail gateway logs: 41 lure deliveries, 3 clicks",
          "x": 60,
          "y": 800,
          "createdAt": "2026-07-09T00:04:46.725Z",
          "stale": {
            "kind": "fresh"
          },
          "type": "evidence",
          "threadId": "o0V81_wVv3JjXJfyj34re"
        },
        "captureMs": 5000
      },
      "nodeId": "TKS4wNrTpCWKTqM8PzbV5",
      "threadId": "o0V81_wVv3JjXJfyj34re"
    },
    {
      "id": "r17Q6QDe6RAkSXa43saEw",
      "seq": 140,
      "at": "2026-07-09T00:05:33.725Z",
      "type": "judgement_declared",
      "payload": {
        "field": "sourceReliability",
        "before": null,
        "after": "B"
      },
      "nodeId": "TKS4wNrTpCWKTqM8PzbV5",
      "threadId": "o0V81_wVv3JjXJfyj34re"
    },
    {
      "id": "OpIDB1QaXpJOL6nN55JbZ",
      "seq": 141,
      "at": "2026-07-09T00:06:20.725Z",
      "type": "judgement_declared",
      "payload": {
        "field": "infoCredibility",
        "before": null,
        "after": 2
      },
      "nodeId": "TKS4wNrTpCWKTqM8PzbV5",
      "threadId": "o0V81_wVv3JjXJfyj34re"
    },
    {
      "id": "1f_FlYhnPjdhvZ9BWQ5_1",
      "seq": 142,
      "at": "2026-07-09T00:07:07.725Z",
      "type": "node_created",
      "payload": {
        "node": {
          "id": "SuvFj9DYwiRofOoIVN9LZ",
          "text": "Passive DNS ties 45.155.87.12 to a 2024 APT-Q campaign",
          "x": 700,
          "y": 800,
          "createdAt": "2026-07-09T00:07:07.725Z",
          "stale": {
            "kind": "fresh"
          },
          "type": "evidence",
          "threadId": "o0V81_wVv3JjXJfyj34re"
        },
        "captureMs": 6000
      },
      "nodeId": "SuvFj9DYwiRofOoIVN9LZ",
      "threadId": "o0V81_wVv3JjXJfyj34re"
    },
    {
      "id": "1c9s020RgZ844bgrc0IS3",
      "seq": 143,
      "at": "2026-07-09T00:07:54.725Z",
      "type": "judgement_declared",
      "payload": {
        "field": "sourceReliability",
        "before": null,
        "after": "C"
      },
      "nodeId": "SuvFj9DYwiRofOoIVN9LZ",
      "threadId": "o0V81_wVv3JjXJfyj34re"
    },
    {
      "id": "wQ1If9K-Rrcb8H6WeUYar",
      "seq": 144,
      "at": "2026-07-09T00:08:41.725Z",
      "type": "judgement_declared",
      "payload": {
        "field": "infoCredibility",
        "before": null,
        "after": 3
      },
      "nodeId": "SuvFj9DYwiRofOoIVN9LZ",
      "threadId": "o0V81_wVv3JjXJfyj34re"
    },
    {
      "id": "-P_bOrPB9u2shJDqijAiW",
      "seq": 145,
      "at": "2026-07-09T00:09:28.725Z",
      "type": "node_created",
      "payload": {
        "node": {
          "id": "TNfNsv_AzGq-_SRR1lY5M",
          "text": "Host serves dozens of unrelated bulletproof clients",
          "x": 1000,
          "y": 800,
          "createdAt": "2026-07-09T00:09:28.725Z",
          "stale": {
            "kind": "fresh"
          },
          "type": "evidence",
          "threadId": "o0V81_wVv3JjXJfyj34re"
        },
        "captureMs": 8000
      },
      "nodeId": "TNfNsv_AzGq-_SRR1lY5M",
      "threadId": "o0V81_wVv3JjXJfyj34re"
    },
    {
      "id": "sxqxVpWoHOLabH19MxYCc",
      "seq": 146,
      "at": "2026-07-09T00:10:15.725Z",
      "type": "judgement_declared",
      "payload": {
        "field": "sourceReliability",
        "before": null,
        "after": "C"
      },
      "nodeId": "TNfNsv_AzGq-_SRR1lY5M",
      "threadId": "o0V81_wVv3JjXJfyj34re"
    },
    {
      "id": "57Qm6lDvg90pZflQEBhsB",
      "seq": 147,
      "at": "2026-07-09T00:11:02.725Z",
      "type": "judgement_declared",
      "payload": {
        "field": "infoCredibility",
        "before": null,
        "after": 3
      },
      "nodeId": "TNfNsv_AzGq-_SRR1lY5M",
      "threadId": "o0V81_wVv3JjXJfyj34re"
    },
    {
      "id": "Z7V3CqzNsSgKKsBiwC7mI",
      "seq": 148,
      "at": "2026-07-09T00:11:49.725Z",
      "type": "edge_created",
      "payload": {
        "edge": {
          "id": "_VHZteb0-OBq0pEx1Kazz",
          "type": "consistent_with",
          "from": "TKS4wNrTpCWKTqM8PzbV5",
          "to": "XhJVHGWTcSHZYdLOsqPtb",
          "createdAt": "2026-07-09T00:11:49.725Z"
        }
      },
      "edgeId": "_VHZteb0-OBq0pEx1Kazz",
      "threadId": "o0V81_wVv3JjXJfyj34re"
    },
    {
      "id": "9S8yF44_ZatAJGYe-S9sc",
      "seq": 149,
      "at": "2026-07-09T00:12:36.725Z",
      "type": "edge_created",
      "payload": {
        "edge": {
          "id": "TcWweRiFwDYmbvT05_V8K",
          "type": "consistent_with",
          "from": "SuvFj9DYwiRofOoIVN9LZ",
          "to": "AvMWn9f1NWbopONzwkucL",
          "createdAt": "2026-07-09T00:12:36.725Z"
        }
      },
      "edgeId": "TcWweRiFwDYmbvT05_V8K",
      "threadId": "o0V81_wVv3JjXJfyj34re"
    },
    {
      "id": "w6lgXYnx5aNBO0pYJM7SC",
      "seq": 150,
      "at": "2026-07-09T00:13:23.725Z",
      "type": "edge_created",
      "payload": {
        "edge": {
          "id": "Q_SRnbdvNBViLtBxzYzVs",
          "type": "inconsistent_with",
          "from": "TNfNsv_AzGq-_SRR1lY5M",
          "to": "_xh2PpXsbBFz5zEu6_rPP",
          "createdAt": "2026-07-09T00:13:23.725Z"
        }
      },
      "edgeId": "Q_SRnbdvNBViLtBxzYzVs",
      "threadId": "o0V81_wVv3JjXJfyj34re"
    },
    {
      "id": "ejIW2jd72ydP6rEGQiLGQ",
      "seq": 151,
      "at": "2026-07-09T00:14:10.725Z",
      "type": "node_created",
      "payload": {
        "node": {
          "id": "4SKTl_F8rO43KM2f-ekhG",
          "text": "Initial access was via the finance-themed phishing wave",
          "x": 1280,
          "y": 620,
          "createdAt": "2026-07-09T00:14:10.725Z",
          "stale": {
            "kind": "fresh"
          },
          "type": "claim",
          "threadId": "o0V81_wVv3JjXJfyj34re",
          "status": "open"
        },
        "captureMs": 4000
      },
      "nodeId": "4SKTl_F8rO43KM2f-ekhG",
      "threadId": "o0V81_wVv3JjXJfyj34re"
    },
    {
      "id": "s0oK34uPgMOxDC6IXymEy",
      "seq": 152,
      "at": "2026-07-09T00:14:57.725Z",
      "type": "judgement_declared",
      "payload": {
        "field": "likelihood",
        "before": null,
        "after": "likely"
      },
      "nodeId": "4SKTl_F8rO43KM2f-ekhG",
      "threadId": "o0V81_wVv3JjXJfyj34re"
    },
    {
      "id": "8xkyagqIpQLCy2o4Afk9w",
      "seq": 153,
      "at": "2026-07-09T00:15:44.725Z",
      "type": "judgement_declared",
      "payload": {
        "field": "confidence",
        "before": null,
        "after": "moderate"
      },
      "nodeId": "4SKTl_F8rO43KM2f-ekhG",
      "threadId": "o0V81_wVv3JjXJfyj34re"
    },
    {
      "id": "TYs9Opvx8WzbqoAk6swoK",
      "seq": 154,
      "at": "2026-07-09T00:16:31.725Z",
      "type": "edge_created",
      "payload": {
        "edge": {
          "id": "3n2CpdsEXcMOR_Ss_GOW7",
          "type": "answers",
          "from": "4SKTl_F8rO43KM2f-ekhG",
          "to": "o0V81_wVv3JjXJfyj34re",
          "createdAt": "2026-07-09T00:16:31.725Z"
        }
      },
      "edgeId": "3n2CpdsEXcMOR_Ss_GOW7",
      "threadId": "o0V81_wVv3JjXJfyj34re"
    },
    {
      "id": "lvc6CsJHp7O75SJP1ZWih",
      "seq": 155,
      "at": "2026-07-09T00:17:18.725Z",
      "type": "judgement_affirmed",
      "payload": {
        "fields": {
          "phase": "delivery",
          "result": "success",
          "direction": "infrastructure_to_victim"
        }
      },
      "nodeId": "zXQvwOk0uFRmHDPKQcJQu",
      "threadId": "o0V81_wVv3JjXJfyj34re"
    },
    {
      "id": "HTTslQDt_oLvVePqez-dj",
      "seq": 156,
      "at": "2026-07-09T00:18:05.725Z",
      "type": "judgement_affirmed",
      "payload": {
        "fields": {
          "phase": "exploitation",
          "result": "success",
          "direction": "infrastructure_to_victim"
        }
      },
      "nodeId": "vFw5lYGhOS0vOJsWAG4jZ",
      "threadId": "o0V81_wVv3JjXJfyj34re"
    },
    {
      "id": "4id-htWRt19fV874oNrD8",
      "seq": 157,
      "at": "2026-07-09T00:18:52.725Z",
      "type": "judgement_affirmed",
      "payload": {
        "fields": {
          "phase": "command_and_control",
          "result": "success",
          "direction": "bidirectional"
        }
      },
      "nodeId": "2QGmwgq7dNoofVc9uR5ze",
      "threadId": "o0V81_wVv3JjXJfyj34re"
    },
    {
      "id": "GeYtn5mLozsibYTWGR9S9",
      "seq": 158,
      "at": "2026-07-09T00:19:39.725Z",
      "type": "judgement_affirmed",
      "payload": {
        "fields": {
          "phase": "actions_on_objectives",
          "result": "success",
          "direction": "victim_to_infrastructure"
        }
      },
      "nodeId": "MSVV96HWDyZKFGz_pQyu5",
      "threadId": "o0V81_wVv3JjXJfyj34re"
    },
    {
      "id": "Ebwz9Gk_Rwlk8yYo3_q22",
      "seq": 159,
      "at": "2026-07-09T00:20:26.725Z",
      "type": "judgement_affirmed",
      "payload": {
        "fields": {
          "confidence": "low"
        }
      },
      "nodeId": "_xh2PpXsbBFz5zEu6_rPP",
      "threadId": "o0V81_wVv3JjXJfyj34re"
    },
    {
      "id": "vmhACzMDhoBaAWf7JL_Ww",
      "seq": 160,
      "at": "2026-07-09T00:21:13.725Z",
      "type": "judgement_affirmed",
      "payload": {
        "fields": {
          "confidence": "moderate"
        }
      },
      "nodeId": "JZCFeln-RZWg65zNpA8d6",
      "threadId": "o0V81_wVv3JjXJfyj34re"
    },
    {
      "id": "O9f2NyZpT8Ss2p7clJ4y_",
      "seq": 161,
      "at": "2026-07-09T00:22:00.725Z",
      "type": "judgement_affirmed",
      "payload": {
        "fields": {
          "confidence": "moderate"
        }
      },
      "nodeId": "XhJVHGWTcSHZYdLOsqPtb",
      "threadId": "o0V81_wVv3JjXJfyj34re"
    },
    {
      "id": "ew6a0a1TFgy2lZc5PBAWu",
      "seq": 162,
      "at": "2026-07-09T00:22:47.725Z",
      "type": "judgement_affirmed",
      "payload": {
        "fields": {
          "confidence": "high"
        }
      },
      "nodeId": "AvMWn9f1NWbopONzwkucL",
      "threadId": "o0V81_wVv3JjXJfyj34re"
    },
    {
      "id": "sWFsJGjkSsenlVF368cDH",
      "seq": 163,
      "at": "2026-07-09T00:23:34.725Z",
      "type": "judgement_affirmed",
      "payload": {
        "fields": {
          "confidence": "high"
        }
      },
      "nodeId": "A93mgK01wEWMR_dKhC2Ya",
      "threadId": "o0V81_wVv3JjXJfyj34re"
    },
    {
      "id": "ZHgz2FwH5fSdWM9noeisz",
      "seq": 164,
      "at": "2026-07-09T00:24:21.725Z",
      "type": "judgement_affirmed",
      "payload": {
        "fields": {
          "likelihood": "likely",
          "confidence": "moderate"
        }
      },
      "nodeId": "4SKTl_F8rO43KM2f-ekhG",
      "threadId": "o0V81_wVv3JjXJfyj34re"
    },
    {
      "id": "lzV-nzKpz9LaYzvsyPiNA",
      "seq": 165,
      "at": "2026-07-10T12:25:17.725Z",
      "type": "judgement_declared",
      "payload": {
        "field": "infoCredibility",
        "before": 2,
        "after": 3
      },
      "nodeId": "wKdNsTR7D9Nqa3Uj0umEF",
      "threadId": "F4Lo07Ls2uXZHq9pHEH73"
    },
    {
      "id": "2VDRCbrpgsH4YAsbJbNlG",
      "seq": 166,
      "at": "2026-07-10T12:26:04.725Z",
      "type": "judgement_affirmed",
      "payload": {
        "fields": {
          "likelihood": "realistic_possibility",
          "confidence": "low"
        }
      },
      "nodeId": "1kMNXyC-mMe4Z_tyEK9hz",
      "threadId": "F4Lo07Ls2uXZHq9pHEH73"
    },
    {
      "id": "0EIpRV_pN1I_enRyiSfuF",
      "seq": 167,
      "at": "2026-07-10T12:26:51.725Z",
      "type": "judgement_declared",
      "payload": {
        "field": "confidence",
        "before": "moderate",
        "after": "high"
      },
      "nodeId": "O1EZzp-7ROLVuI10h51tp",
      "threadId": "edWnPwcXCSAfJnQc_cb6G"
    }
  ]
}